{"g":{"mid":1516377156457,"gid":"0021700471","gdte":"2017-12-22","htm":"2017-12-22T19:00:00","vtm":"2017-12-22T19:00:00","etm":"2017-12-22T19:00:00","gdtutc":"2017-12-23","utctm":"00:00","ac":"Detroit","as":"MI","gcode":"20171222/NYKDET","next":"http://data.nba.com/data/v2015/json/mobile_teams/nba/2017/scores/gamedetail/0021700471_gamedetail.json","ar":0,"p":4,"st":3,"stt":"Final","cl":"00:00.0","lpla":{"evt":638,"cl":"00:00.0","de":"End Period","locX":0,"locY":-80,"opt1":0,"opt2":0,"mtype":0,"etype":13,"opid":"","tid":0,"pid":0,"hs":104,"vs":101,"epid":"","oftid":1610612752},"vls":{"q1":21,"s":101,"ftout":0,"stout":0,"ta":"NYK","tstsg":{"fga":97,"fgm":44,"tpa":24,"tpm":8,"fta":6,"ftm":5,"oreb":16,"dreb":35,"reb":51,"ast":25,"stl":6,"blk":9,"pf":20,"tov":14,"fbpts":0,"fbptsa":2,"fbptsm":0,"pip":54,"pipa":50,"pipm":27,"ble":5,"bpts":27,"tf":1,"scp":18,"tmreb":10,"tmtov":1,"potov":6},"pstsg":[{"fn":"Kristaps","ln":"Porzingis","num":"6","pos":"SF","min":38,"sec":22,"totsec":2302,"fga":28,"fgm":12,"tpa":9,"tpm":3,"fta":2,"ftm":2,"oreb":2,"dreb":7,"reb":9,"ast":2,"stl":1,"blk":1,"pf":4,"pts":29,"tov":3,"fbpts":0,"fbptsa":0,"fbptsm":0,"pip":8,"pipa":9,"pipm":4,"court":1,"pid":204001,"pm":13,"blka":0,"tf":0,"status":"A","memo":""},{"fn":"Lance","ln":"Thomas","num":"42","pos":"PF","min":34,"sec":39,"totsec":2079,"fga":8,"fgm":1,"tpa":3,"tpm":1,"fta":0,"ftm":0,"oreb":1,"dreb":6,"reb":7,"ast":1,"stl":1,"blk":0,"pf":2,"pts":3,"tov":1,"fbpts":0,"fbptsa":2,"fbptsm":0,"pip":0,"pipa":5,"pipm":0,"court":0,"pid":202498,"pm":13,"blka":2,"tf":0,"status":"A","memo":""},{"fn":"Enes","ln":"Kanter","num":"00","pos":"C","min":29,"sec":27,"totsec":1767,"fga":17,"fgm":11,"tpa":0,"tpm":0,"fta":0,"ftm":0,"oreb":8,"dreb":8,"reb":16,"ast":3,"stl":1,"blk":3,"pf":3,"pts":22,"tov":1,"fbpts":0,"fbptsa":0,"fbptsm":0,"pip":22,"pipa":16,"pipm":11,"court":0,"pid":202683,"pm":17,"blka":2,"tf":0,"status":"A","memo":""},{"fn":"Jarrett","ln":"Jack","num":"55","pos":"SG","min":28,"sec":5,"totsec":1685,"fga":5,"fgm":2,"tpa":1,"tpm":0,"fta":0,"ftm":0,"oreb":0,"dreb":6,"reb":6,"ast":6,"stl":1,"blk":0,"pf":6,"pts":4,"tov":2,"fbpts":0,"fbptsa":0,"fbptsm":0,"pip":4,"pipa":3,"pipm":2,"court":0,"pid":101127,"pm":3,"blka":0,"tf":0,"status":"A","memo":""},{"fn":"Courtney","ln":"Lee","num":"5","pos":"PG","min":33,"sec":37,"totsec":2017,"fga":15,"fgm":6,"tpa":5,"tpm":2,"fta":2,"ftm":2,"oreb":1,"dreb":4,"reb":5,"ast":4,"stl":1,"blk":0,"pf":2,"pts":16,"tov":1,"fbpts":0,"fbptsa":0,"fbptsm":0,"pip":6,"pipa":6,"pipm":3,"court":1,"pid":201584,"pm":12,"blka":1,"tf":0,"status":"A","memo":""},{"fn":"Frank","ln":"Ntilikina","num":"11","pos":"","min":19,"sec":54,"totsec":1194,"fga":3,"fgm":2,"tpa":2,"tpm":1,"fta":0,"ftm":0,"oreb":0,"dreb":2,"reb":2,"ast":3,"stl":0,"blk":0,"pf":1,"pts":5,"tov":1,"fbpts":0,"fbptsa":0,"fbptsm":0,"pip":0,"pipa":0,"pipm":0,"court":1,"pid":1628373,"pm":-6,"blka":0,"tf":0,"status":"A","memo":""},{"fn":"Doug","ln":"McDermott","num":"20","pos":"","min":16,"sec":21,"totsec":981,"fga":7,"fgm":4,"tpa":2,"tpm":1,"fta":2,"ftm":1,"oreb":0,"dreb":0,"reb":0,"ast":0,"stl":0,"blk":2,"pf":0,"pts":10,"tov":1,"fbpts":0,"fbptsa":0,"fbptsm":0,"pip":2,"pipa":1,"pipm":1,"court":1,"pid":203926,"pm":-17,"blka":0,"tf":0,"status":"A","memo":""},{"fn":"Kyle","ln":"O'Quinn","num":"9","pos":"","min":11,"sec":40,"totsec":700,"fga":3,"fgm":2,"tpa":0,"tpm":0,"fta":0,"ftm":0,"oreb":0,"dreb":2,"reb":2,"ast":3,"stl":0,"blk":3,"pf":2,"pts":4,"tov":0,"fbpts":0,"fbptsa":0,"fbptsm":0,"pip":4,"pipa":3,"pipm":2,"court":0,"pid":203124,"pm":-18,"blka":0,"tf":0,"status":"A","memo":""},{"fn":"Michael","ln":"Beasley","num":"8","pos":"","min":13,"sec":1,"totsec":781,"fga":6,"fgm":3,"tpa":0,"tpm":0,"fta":0,"ftm":0,"oreb":2,"dreb":0,"reb":2,"ast":3,"stl":0,"blk":0,"pf":0,"pts":6,"tov":2,"fbpts":0,"fbptsa":0,"fbptsm":0,"pip":6,"pipa":4,"pipm":3,"court":1,"pid":201563,"pm":-19,"blka":0,"tf":0,"status":"A","memo":""},{"fn":"Ron","ln":"Baker","num":"31","pos":"","min":11,"sec":41,"totsec":701,"fga":3,"fgm":1,"tpa":2,"tpm":0,"fta":0,"ftm":0,"oreb":0,"dreb":0,"reb":0,"ast":0,"stl":1,"blk":0,"pf":0,"pts":2,"tov":1,"fbpts":0,"fbptsa":0,"fbptsm":0,"pip":2,"pipa":1,"pipm":1,"court":0,"pid":1627758,"pm":-15,"blka":0,"tf":0,"status":"A","memo":""},{"fn":"Joakim","ln":"Noah","num":"13","pos":"","min":3,"sec":8,"totsec":188,"fga":2,"fgm":0,"tpa":0,"tpm":0,"fta":0,"ftm":0,"oreb":2,"dreb":0,"reb":2,"ast":0,"stl":0,"blk":0,"pf":0,"pts":0,"tov":1,"fbpts":0,"fbptsa":0,"fbptsm":0,"pip":0,"pipa":2,"pipm":0,"court":0,"pid":201149,"pm":2,"blka":0,"tf":0,"status":"A","memo":""},{"fn":"Willy","ln":"Hernangomez","num":"14","pos":"","min":0,"sec":0,"totsec":0,"fga":0,"fgm":0,"tpa":0,"tpm":0,"fta":0,"ftm":0,"oreb":0,"dreb":0,"reb":0,"ast":0,"stl":0,"blk":0,"pf":0,"pts":0,"tov":0,"fbpts":0,"fbptsa":0,"fbptsm":0,"pip":0,"pipa":0,"pipm":0,"court":0,"pid":1626195,"pm":0,"blka":0,"tf":0,"status":"A","memo":""},{"fn":"Ramon","ln":"Sessions","num":"1","pos":"","min":0,"sec":0,"totsec":0,"fga":0,"fgm":0,"tpa":0,"tpm":0,"fta":0,"ftm":0,"oreb":0,"dreb":0,"reb":0,"ast":0,"stl":0,"blk":0,"pf":0,"pts":0,"tov":0,"fbpts":0,"fbptsa":0,"fbptsm":0,"pip":0,"pipa":0,"pipm":0,"court":0,"pid":201196,"pm":0,"blka":0,"tf":0,"status":"A","memo":""},{"fn":"Damyean","ln":"Dotson","num":"21","pos":"","min":0,"sec":0,"totsec":0,"fga":0,"fgm":0,"tpa":0,"tpm":0,"fta":0,"ftm":0,"oreb":0,"dreb":0,"reb":0,"ast":0,"stl":0,"blk":0,"pf":0,"pts":0,"tov":0,"fbpts":0,"fbptsa":0,"fbptsm":0,"pip":0,"pipa":0,"pipm":0,"court":0,"pid":1628422,"pm":0,"blka":0,"tf":0,"status":"I","memo":""},{"fn":"Tim","ln":"Hardaway Jr.","num":"3","pos":"","min":0,"sec":0,"totsec":0,"fga":0,"fgm":0,"tpa":0,"tpm":0,"fta":0,"ftm":0,"oreb":0,"dreb":0,"reb":0,"ast":0,"stl":0,"blk":0,"pf":0,"pts":0,"tov":0,"fbpts":0,"fbptsa":0,"fbptsm":0,"pip":0,"pipa":0,"pipm":0,"court":0,"pid":203501,"pm":0,"blka":0,"tf":1,"status":"I","memo":""},{"fn":"Isaiah","ln":"Hicks","num":"4","pos":"","min":0,"sec":0,"totsec":0,"fga":0,"fgm":0,"tpa":0,"tpm":0,"fta":0,"ftm":0,"oreb":0,"dreb":0,"reb":0,"ast":0,"stl":0,"blk":0,"pf":0,"pts":0,"tov":0,"fbpts":0,"fbptsa":0,"fbptsm":0,"pip":0,"pipa":0,"pipm":0,"court":0,"pid":1628439,"pm":0,"blka":0,"tf":0,"status":"I","memo":""},{"fn":"Luke","ln":"Kornet","num":"2","pos":"","min":0,"sec":0,"totsec":0,"fga":0,"fgm":0,"tpa":0,"tpm":0,"fta":0,"ftm":0,"oreb":0,"dreb":0,"reb":0,"ast":0,"stl":0,"blk":0,"pf":0,"pts":0,"tov":0,"fbpts":0,"fbptsa":0,"fbptsm":0,"pip":0,"pipa":0,"pipm":0,"court":0,"pid":1628436,"pm":0,"blka":0,"tf":0,"status":"I","memo":""}],"tn":"Knicks","tc":"New York","tid":1610612752,"q2":23,"q3":31,"q4":26,"ot1":0,"ot2":0,"ot3":0,"ot4":0,"ot5":0,"ot6":0,"ot7":0,"ot8":0,"ot9":0,"ot10":0},"hls":{"q1":25,"s":104,"ftout":2,"stout":0,"ta":"DET","tstsg":{"fga":88,"fgm":38,"tpa":25,"tpm":10,"fta":25,"ftm":18,"oreb":15,"dreb":29,"reb":44,"ast":19,"stl":8,"blk":5,"pf":11,"tov":11,"fbpts":15,"fbptsa":6,"fbptsm":6,"pip":52,"pipa":52,"pipm":26,"ble":13,"bpts":26,"tf":1,"scp":21,"tmreb":6,"tmtov":1,"potov":11},"pstsg":[{"fn":"Anthony","ln":"Tolliver","num":"43","pos":"SF","min":35,"sec":15,"totsec":2115,"fga":11,"fgm":3,"tpa":10,"tpm":3,"fta":4,"ftm":3,"oreb":1,"dreb":2,"reb":3,"ast":0,"stl":1,"blk":1,"pf":3,"pts":12,"tov":2,"fbpts":0,"fbptsa":0,"fbptsm":0,"pip":0,"pipa":1,"pipm":0,"court":1,"pid":201229,"pm":-15,"blka":0,"tf":0,"status":"A","memo":""},{"fn":"Tobias","ln":"Harris","num":"34","pos":"PF","min":41,"sec":3,"totsec":2463,"fga":16,"fgm":7,"tpa":6,"tpm":3,"fta":10,"ftm":7,"oreb":1,"dreb":2,"reb":3,"ast":5,"stl":0,"blk":1,"pf":1,"pts":24,"tov":1,"fbpts":5,"fbptsa":1,"fbptsm":1,"pip":8,"pipa":7,"pipm":4,"court":1,"pid":202699,"pm":14,"blka":2,"tf":0,"status":"A","memo":""},{"fn":"Andre","ln":"Drummond","num":"0","pos":"C","min":26,"sec":1,"totsec":1561,"fga":16,"fgm":8,"tpa":0,"tpm":0,"fta":4,"ftm":2,"oreb":7,"dreb":8,"reb":15,"ast":1,"stl":1,"blk":2,"pf":3,"pts":18,"tov":2,"fbpts":2,"fbptsa":1,"fbptsm":1,"pip":16,"pipa":16,"pipm":8,"court":0,"pid":203083,"pm":-10,"blka":1,"tf":0,"status":"A","memo":""},{"fn":"Reggie","ln":"Bullock","num":"25","pos":"SG","min":30,"sec":5,"totsec":1805,"fga":8,"fgm":6,"tpa":3,"tpm":2,"fta":0,"ftm":0,"oreb":1,"dreb":5,"reb":6,"ast":0,"stl":1,"blk":1,"pf":1,"pts":14,"tov":1,"fbpts":4,"fbptsa":2,"fbptsm":2,"pip":8,"pipa":5,"pipm":4,"court":1,"pid":203493,"pm":-13,"blka":0,"tf":0,"status":"A","memo":""},{"fn":"Reggie","ln":"Jackson","num":"1","pos":"PG","min":28,"sec":18,"totsec":1698,"fga":12,"fgm":3,"tpa":3,"tpm":0,"fta":5,"ftm":4,"oreb":0,"dreb":4,"reb":4,"ast":8,"stl":0,"blk":0,"pf":0,"pts":10,"tov":2,"fbpts":0,"fbptsa":0,"fbptsm":0,"pip":4,"pipa":6,"pipm":2,"court":1,"pid":202704,"pm":-4,"blka":1,"tf":1,"status":"A","memo":""},{"fn":"Eric","ln":"Moreland","num":"24","pos":"","min":21,"sec":35,"totsec":1295,"fga":4,"fgm":2,"tpa":0,"tpm":0,"fta":0,"ftm":0,"oreb":2,"dreb":3,"reb":5,"ast":0,"stl":2,"blk":0,"pf":2,"pts":4,"tov":0,"fbpts":0,"fbptsa":0,"fbptsm":0,"pip":4,"pipa":4,"pipm":2,"court":0,"pid":203961,"pm":11,"blka":2,"tf":0,"status":"A","memo":""},{"fn":"Stanley","ln":"Johnson","num":"7","pos":"","min":20,"sec":5,"totsec":1205,"fga":8,"fgm":4,"tpa":3,"tpm":2,"fta":2,"ftm":2,"oreb":1,"dreb":2,"reb":3,"ast":0,"stl":2,"blk":0,"pf":0,"pts":12,"tov":1,"fbpts":0,"fbptsa":0,"fbptsm":0,"pip":2,"pipa":4,"pipm":1,"court":1,"pid":1626169,"pm":9,"blka":1,"tf":0,"status":"A","memo":""},{"fn":"Ish","ln":"Smith","num":"14","pos":"","min":19,"sec":42,"totsec":1182,"fga":10,"fgm":5,"tpa":0,"tpm":0,"fta":0,"ftm":0,"oreb":2,"dreb":2,"reb":4,"ast":4,"stl":1,"blk":0,"pf":0,"pts":10,"tov":2,"fbpts":4,"fbptsa":2,"fbptsm":2,"pip":10,"pipa":7,"pipm":5,"court":0,"pid":202397,"pm":7,"blka":1,"tf":0,"status":"A","memo":""},{"fn":"Luke","ln":"Kennard","num":"5","pos":"","min":17,"sec":55,"totsec":1075,"fga":3,"fgm":0,"tpa":0,"tpm":0,"fta":0,"ftm":0,"oreb":0,"dreb":1,"reb":1,"ast":1,"stl":0,"blk":0,"pf":1,"pts":0,"tov":0,"fbpts":0,"fbptsa":0,"fbptsm":0,"pip":0,"pipa":2,"pipm":0,"court":0,"pid":1628379,"pm":16,"blka":1,"tf":0,"status":"A","memo":""},{"fn":"Avery","ln":"Bradley","num":"22","pos":"","min":0,"sec":0,"totsec":0,"fga":0,"fgm":0,"tpa":0,"tpm":0,"fta":0,"ftm":0,"oreb":0,"dreb":0,"reb":0,"ast":0,"stl":0,"blk":0,"pf":0,"pts":0,"tov":0,"fbpts":0,"fbptsa":0,"fbptsm":0,"pip":0,"pipa":0,"pipm":0,"court":0,"pid":202340,"pm":0,"blka":0,"tf":0,"status":"A","memo":""},{"fn":"Henry","ln":"Ellenson","num":"8","pos":"","min":0,"sec":0,"totsec":0,"fga":0,"fgm":0,"tpa":0,"tpm":0,"fta":0,"ftm":0,"oreb":0,"dreb":0,"reb":0,"ast":0,"stl":0,"blk":0,"pf":0,"pts":0,"tov":0,"fbpts":0,"fbptsa":0,"fbptsm":0,"pip":0,"pipa":0,"pipm":0,"court":0,"pid":1627740,"pm":0,"blka":0,"tf":0,"status":"A","memo":""},{"fn":"Langston","ln":"Galloway","num":"9","pos":"","min":0,"sec":0,"totsec":0,"fga":0,"fgm":0,"tpa":0,"tpm":0,"fta":0,"ftm":0,"oreb":0,"dreb":0,"reb":0,"ast":0,"stl":0,"blk":0,"pf":0,"pts":0,"tov":0,"fbpts":0,"fbptsa":0,"fbptsm":0,"pip":0,"pipa":0,"pipm":0,"court":0,"pid":204038,"pm":0,"blka":0,"tf":0,"status":"A","memo":""},{"fn":"Boban","ln":"Marjanovic","num":"51","pos":"","min":0,"sec":0,"totsec":0,"fga":0,"fgm":0,"tpa":0,"tpm":0,"fta":0,"ftm":0,"oreb":0,"dreb":0,"reb":0,"ast":0,"stl":0,"blk":0,"pf":0,"pts":0,"tov":0,"fbpts":0,"fbptsa":0,"fbptsm":0,"pip":0,"pipa":0,"pipm":0,"court":0,"pid":1626246,"pm":0,"blka":0,"tf":0,"status":"A","memo":""},{"fn":"Dwight","ln":"Buycks","num":"20","pos":"","min":0,"sec":0,"totsec":0,"fga":0,"fgm":0,"tpa":0,"tpm":0,"fta":0,"ftm":0,"oreb":0,"dreb":0,"reb":0,"ast":0,"stl":0,"blk":0,"pf":0,"pts":0,"tov":0,"fbpts":0,"fbptsa":0,"fbptsm":0,"pip":0,"pipa":0,"pipm":0,"court":0,"pid":202779,"pm":0,"blka":0,"tf":0,"status":"I","memo":""},{"fn":"Jon","ln":"Leuer","num":"30","pos":"","min":0,"sec":0,"totsec":0,"fga":0,"fgm":0,"tpa":0,"tpm":0,"fta":0,"ftm":0,"oreb":0,"dreb":0,"reb":0,"ast":0,"stl":0,"blk":0,"pf":0,"pts":0,"tov":0,"fbpts":0,"fbptsa":0,"fbptsm":0,"pip":0,"pipa":0,"pipm":0,"court":0,"pid":202720,"pm":0,"blka":0,"tf":0,"status":"I","memo":""},{"fn":"Luis","ln":"Montero","num":"44","pos":"","min":0,"sec":0,"totsec":0,"fga":0,"fgm":0,"tpa":0,"tpm":0,"fta":0,"ftm":0,"oreb":0,"dreb":0,"reb":0,"ast":0,"stl":0,"blk":0,"pf":0,"pts":0,"tov":0,"fbpts":0,"fbptsa":0,"fbptsm":0,"pip":0,"pipa":0,"pipm":0,"court":0,"pid":1626242,"pm":0,"blka":0,"tf":0,"status":"I","memo":""}],"tn":"Pistons","tc":"Detroit","tid":1610612765,"q2":27,"q3":22,"q4":30,"ot1":0,"ot2":0,"ot3":0,"ot4":0,"ot5":0,"ot6":0,"ot7":0,"ot8":0,"ot9":0,"ot10":0},"offs":{"off":[{"fn":"Eric","ln":"Lewis","num":"42"},{"fn":"Nick","ln":"Buchert","num":"3"},{"fn":"Lauren","ln":"Holtkamp","num":"7"}]},"an":"Little Caesars Arena","at":16922,"gsts":{"lc":4,"tt":7},"dur":"2:04"}}