{"g":{"mid":1446789944110,"gid":"0021500074","gdte":"2015-11-05","htm":"2015-11-05T19:30:00","vtm":"2015-11-05T21:30:00","etm":"2015-11-05T22:30:00","gdtutc":"2015-11-06","utctm":"03:30","ac":"Portland","as":"OR","gcode":"20151105/MEMPOR","next":"http://data.nba.com/data/v2015/json/mobile_teams/nba/2015/scores/gamedetail/0021500074_gamedetail.json","ar":0,"p":4,"st":3,"stt":"Final","cl":"00:00.0","lpla":{"evt":485,"cl":"00:00.0","de":"End Period","locX":0,"locY":-80,"opt1":0,"opt2":0,"mtype":0,"etype":13,"opid":"","tid":0,"pid":0,"hs":115,"vs":96,"epid":"","oftid":1610612757},"vls":{"q1":23,"s":96,"ftout":1,"stout":2,"ta":"MEM","tstsg":{"fga":77,"fgm":37,"tpa":20,"tpm":7,"fta":21,"ftm":15,"oreb":7,"dreb":29,"reb":36,"ast":20,"stl":4,"blk":5,"pf":14,"tov":8,"fbpts":4,"fbptsa":2,"fbptsm":2,"pip":36,"pipa":32,"pipm":18,"ble":5,"bpts":34,"tf":0,"scp":15},"pstsg":[{"fn":"Tony","ln":"Allen","num":" 9","pos":"F","min":23,"fga":6,"fgm":3,"tpa":1,"tpm":0,"fta":0,"ftm":0,"oreb":0,"dreb":1,"reb":1,"ast":1,"stl":0,"blk":1,"pf":3,"pts":6,"tov":0,"fbpts":2,"fbptsa":1,"fbptsm":1,"pip":4,"pipa":2,"pipm":2,"court":0,"pid":2754,"pm":-11,"blka":0,"tf":0,"status":"A"},{"fn":"Zach","ln":"Randolph","num":"50","pos":"F","min":32,"fga":12,"fgm":8,"tpa":0,"tpm":0,"fta":0,"ftm":0,"oreb":2,"dreb":8,"reb":10,"ast":2,"stl":1,"blk":0,"pf":1,"pts":16,"tov":3,"fbpts":0,"fbptsa":0,"fbptsm":0,"pip":10,"pipa":7,"pipm":5,"court":0,"pid":2216,"pm":-14,"blka":1,"tf":0,"status":"A"},{"fn":"Marc","ln":"Gasol","num":"33","pos":"C","min":27,"fga":13,"fgm":4,"tpa":0,"tpm":0,"fta":10,"ftm":7,"oreb":1,"dreb":4,"reb":5,"ast":3,"stl":0,"blk":2,"pf":2,"pts":15,"tov":1,"fbpts":0,"fbptsa":0,"fbptsm":0,"pip":8,"pipa":8,"pipm":4,"court":0,"pid":201188,"pm":-21,"blka":0,"tf":0,"status":"A"},{"fn":"Courtney","ln":"Lee","num":" 5","pos":"G","min":30,"fga":10,"fgm":6,"tpa":6,"tpm":3,"fta":4,"ftm":3,"oreb":1,"dreb":1,"reb":2,"ast":0,"stl":1,"blk":0,"pf":0,"pts":18,"tov":0,"fbpts":0,"fbptsa":0,"fbptsm":0,"pip":4,"pipa":3,"pipm":2,"court":0,"pid":201584,"pm":-13,"blka":0,"tf":0,"status":"A"},{"fn":"Mike","ln":"Conley","num":"11","pos":"G","min":31,"fga":8,"fgm":2,"tpa":2,"tpm":0,"fta":4,"ftm":3,"oreb":0,"dreb":2,"reb":2,"ast":3,"stl":0,"blk":0,"pf":0,"pts":7,"tov":2,"fbpts":0,"fbptsa":0,"fbptsm":0,"pip":4,"pipa":5,"pipm":2,"court":0,"pid":201144,"pm":-19,"blka":0,"tf":0,"status":"A"},{"fn":"Beno","ln":"Udrih","num":"19","pos":"","min":15,"fga":5,"fgm":4,"tpa":1,"tpm":1,"fta":0,"ftm":0,"oreb":0,"dreb":0,"reb":0,"ast":6,"stl":0,"blk":0,"pf":2,"pts":9,"tov":0,"fbpts":2,"fbptsa":1,"fbptsm":1,"pip":0,"pipa":0,"pipm":0,"court":1,"pid":2757,"pm":0,"blka":1,"tf":0,"status":"A"},{"fn":"Jeff","ln":"Green","num":"32","pos":"","min":19,"fga":8,"fgm":3,"tpa":3,"tpm":0,"fta":0,"ftm":0,"oreb":0,"dreb":2,"reb":2,"ast":0,"stl":1,"blk":0,"pf":1,"pts":6,"tov":1,"fbpts":0,"fbptsa":0,"fbptsm":0,"pip":2,"pipa":2,"pipm":1,"court":0,"pid":201145,"pm":-14,"blka":0,"tf":0,"status":"A"},{"fn":"JaMychal","ln":"Green","num":" 0","pos":"","min":10,"fga":4,"fgm":3,"tpa":2,"tpm":2,"fta":0,"ftm":0,"oreb":0,"dreb":3,"reb":3,"ast":0,"stl":1,"blk":0,"pf":1,"pts":8,"tov":0,"fbpts":0,"fbptsa":0,"fbptsm":0,"pip":0,"pipa":1,"pipm":0,"court":1,"pid":203210,"pm":4,"blka":1,"tf":0,"status":"A"},{"fn":"Matt","ln":"Barnes","num":"22","pos":"","min":24,"fga":6,"fgm":2,"tpa":4,"tpm":1,"fta":0,"ftm":0,"oreb":1,"dreb":4,"reb":5,"ast":3,"stl":0,"blk":1,"pf":3,"pts":5,"tov":0,"fbpts":0,"fbptsa":0,"fbptsm":0,"pip":2,"pipa":1,"pipm":1,"court":0,"pid":2440,"pm":-13,"blka":0,"tf":0,"status":"A"},{"fn":"Brandan","ln":"Wright","num":"34","pos":"","min":17,"fga":4,"fgm":2,"tpa":0,"tpm":0,"fta":3,"ftm":2,"oreb":1,"dreb":3,"reb":4,"ast":0,"stl":0,"blk":1,"pf":1,"pts":6,"tov":0,"fbpts":0,"fbptsa":0,"fbptsm":0,"pip":2,"pipa":3,"pipm":1,"court":1,"pid":201148,"pm":-4,"blka":0,"tf":0,"status":"A"},{"fn":"Russ","ln":"Smith","num":" 2","pos":"","min":3,"fga":1,"fgm":0,"tpa":1,"tpm":0,"fta":0,"ftm":0,"oreb":0,"dreb":0,"reb":0,"ast":2,"stl":0,"blk":0,"pf":0,"pts":0,"tov":1,"fbpts":0,"fbptsa":0,"fbptsm":0,"pip":0,"pipa":0,"pipm":0,"court":1,"pid":203893,"pm":5,"blka":0,"tf":0,"status":"A"},{"fn":"Jarnell","ln":"Stokes","num":" 1","pos":"","min":3,"fga":0,"fgm":0,"tpa":0,"tpm":0,"fta":0,"ftm":0,"oreb":1,"dreb":1,"reb":2,"ast":0,"stl":0,"blk":0,"pf":0,"pts":0,"tov":0,"fbpts":0,"fbptsa":0,"fbptsm":0,"pip":0,"pipa":0,"pipm":0,"court":1,"pid":203950,"pm":5,"blka":0,"tf":0,"status":"A"},{"fn":"Vince","ln":"Carter","num":"15","pos":"","min":0,"fga":0,"fgm":0,"tpa":0,"tpm":0,"fta":0,"ftm":0,"oreb":0,"dreb":0,"reb":0,"ast":0,"stl":0,"blk":0,"pf":0,"pts":0,"tov":0,"fbpts":0,"fbptsa":0,"fbptsm":0,"pip":0,"pipa":0,"pipm":0,"court":0,"pid":1713,"pm":0,"blka":0,"tf":0,"status":"A"},{"fn":"Jordan","ln":"Adams","num":" 3","pos":"","min":0,"fga":0,"fgm":0,"tpa":0,"tpm":0,"fta":0,"ftm":0,"oreb":0,"dreb":0,"reb":0,"ast":0,"stl":0,"blk":0,"pf":0,"pts":0,"tov":0,"fbpts":0,"fbptsa":0,"fbptsm":0,"pip":0,"pipa":0,"pipm":0,"court":0,"pid":203919,"pm":0,"blka":0,"tf":0,"status":"I"},{"fn":"Jarell","ln":"Martin","num":"10","pos":"","min":0,"fga":0,"fgm":0,"tpa":0,"tpm":0,"fta":0,"ftm":0,"oreb":0,"dreb":0,"reb":0,"ast":0,"stl":0,"blk":0,"pf":0,"pts":0,"tov":0,"fbpts":0,"fbptsa":0,"fbptsm":0,"pip":0,"pipa":0,"pipm":0,"court":0,"pid":1626185,"pm":0,"blka":0,"tf":0,"status":"I"}],"tn":"Grizzlies","tc":"Memphis","tid":1610612763,"q2":23,"q3":25,"q4":25,"ot1":0,"ot2":0,"ot3":0,"ot4":0,"ot5":0,"ot6":0,"ot7":0,"ot8":0,"ot9":0,"ot10":0},"hls":{"q1":18,"s":115,"ftout":1,"stout":2,"ta":"POR","tstsg":{"fga":87,"fgm":44,"tpa":30,"tpm":15,"fta":20,"ftm":12,"oreb":14,"dreb":33,"reb":47,"ast":29,"stl":3,"blk":3,"pf":19,"tov":8,"fbpts":4,"fbptsa":2,"fbptsm":2,"pip":40,"pipa":35,"pipm":20,"ble":26,"bpts":35,"tf":0,"scp":20},"pstsg":[{"fn":"Al-Farouq","ln":"Aminu","num":" 8","pos":"F","min":33,"fga":11,"fgm":4,"tpa":4,"tpm":1,"fta":4,"ftm":2,"oreb":2,"dreb":8,"reb":10,"ast":5,"stl":1,"blk":0,"pf":4,"pts":11,"tov":2,"fbpts":0,"fbptsa":0,"fbptsm":0,"pip":6,"pipa":7,"pipm":3,"court":0,"pid":202329,"pm":11,"blka":0,"tf":0,"status":"A"},{"fn":"Meyers","ln":"Leonard","num":"11","pos":"F","min":27,"fga":7,"fgm":5,"tpa":3,"tpm":1,"fta":3,"ftm":3,"oreb":1,"dreb":4,"reb":5,"ast":2,"stl":0,"blk":0,"pf":5,"pts":14,"tov":0,"fbpts":2,"fbptsa":1,"fbptsm":1,"pip":6,"pipa":3,"pipm":3,"court":0,"pid":203086,"pm":19,"blka":0,"tf":0,"status":"A"},{"fn":"Mason","ln":"Plumlee","num":"24","pos":"C","min":21,"fga":6,"fgm":4,"tpa":0,"tpm":0,"fta":2,"ftm":0,"oreb":5,"dreb":7,"reb":12,"ast":3,"stl":1,"blk":0,"pf":4,"pts":8,"tov":0,"fbpts":2,"fbptsa":1,"fbptsm":1,"pip":8,"pipa":6,"pipm":4,"court":0,"pid":203486,"pm":1,"blka":1,"tf":0,"status":"A"},{"fn":"CJ","ln":"McCollum","num":" 3","pos":"G","min":30,"fga":18,"fgm":7,"tpa":6,"tpm":4,"fta":3,"ftm":2,"oreb":2,"dreb":2,"reb":4,"ast":5,"stl":0,"blk":0,"pf":2,"pts":20,"tov":1,"fbpts":0,"fbptsa":0,"fbptsm":0,"pip":2,"pipa":3,"pipm":1,"court":0,"pid":203468,"pm":13,"blka":1,"tf":0,"status":"A"},{"fn":"Damian","ln":"Lillard","num":" 0","pos":"G","min":32,"fga":18,"fgm":9,"tpa":11,"tpm":7,"fta":2,"ftm":2,"oreb":1,"dreb":0,"reb":1,"ast":5,"stl":0,"blk":1,"pf":0,"pts":27,"tov":0,"fbpts":0,"fbptsa":0,"fbptsm":0,"pip":4,"pipa":4,"pipm":2,"court":0,"pid":203081,"pm":24,"blka":1,"tf":0,"status":"A"},{"fn":"Noah","ln":"Vonleh","num":"21","pos":"","min":11,"fga":4,"fgm":1,"tpa":2,"tpm":0,"fta":0,"ftm":0,"oreb":0,"dreb":3,"reb":3,"ast":0,"stl":0,"blk":2,"pf":1,"pts":2,"tov":2,"fbpts":0,"fbptsa":0,"fbptsm":0,"pip":0,"pipa":1,"pipm":0,"court":1,"pid":203943,"pm":-11,"blka":1,"tf":0,"status":"A"},{"fn":"Allen","ln":"Crabbe","num":"23","pos":"","min":21,"fga":7,"fgm":5,"tpa":1,"tpm":1,"fta":0,"ftm":0,"oreb":0,"dreb":1,"reb":1,"ast":3,"stl":1,"blk":0,"pf":1,"pts":11,"tov":1,"fbpts":0,"fbptsa":0,"fbptsm":0,"pip":0,"pipa":0,"pipm":0,"court":0,"pid":203459,"pm":18,"blka":0,"tf":0,"status":"A"},{"fn":"Ed","ln":"Davis","num":"17","pos":"","min":22,"fga":5,"fgm":4,"tpa":0,"tpm":0,"fta":3,"ftm":1,"oreb":1,"dreb":7,"reb":8,"ast":2,"stl":0,"blk":0,"pf":1,"pts":9,"tov":1,"fbpts":0,"fbptsa":0,"fbptsm":0,"pip":6,"pipa":4,"pipm":3,"court":0,"pid":202334,"pm":23,"blka":0,"tf":0,"status":"A"},{"fn":"Maurice","ln":"Harkless","num":" 4","pos":"","min":25,"fga":7,"fgm":4,"tpa":2,"tpm":0,"fta":3,"ftm":2,"oreb":2,"dreb":1,"reb":3,"ast":4,"stl":0,"blk":0,"pf":1,"pts":10,"tov":0,"fbpts":0,"fbptsa":0,"fbptsm":0,"pip":8,"pipa":5,"pipm":4,"court":0,"pid":203090,"pm":17,"blka":1,"tf":0,"status":"A"},{"fn":"Pat","ln":"Connaughton","num":" 5","pos":"","min":3,"fga":1,"fgm":0,"tpa":0,"tpm":0,"fta":0,"ftm":0,"oreb":0,"dreb":0,"reb":0,"ast":0,"stl":0,"blk":0,"pf":0,"pts":0,"tov":1,"fbpts":0,"fbptsa":0,"fbptsm":0,"pip":0,"pipa":1,"pipm":0,"court":1,"pid":1626192,"pm":-5,"blka":0,"tf":0,"status":"A"},{"fn":"Chris","ln":"Kaman","num":"35","pos":"","min":3,"fga":2,"fgm":0,"tpa":0,"tpm":0,"fta":0,"ftm":0,"oreb":0,"dreb":0,"reb":0,"ast":0,"stl":0,"blk":0,"pf":0,"pts":0,"tov":0,"fbpts":0,"fbptsa":0,"fbptsm":0,"pip":0,"pipa":1,"pipm":0,"court":1,"pid":2549,"pm":-5,"blka":0,"tf":0,"status":"A"},{"fn":"Luis","ln":"Montero","num":"44","pos":"","min":3,"fga":1,"fgm":1,"tpa":1,"tpm":1,"fta":0,"ftm":0,"oreb":0,"dreb":0,"reb":0,"ast":0,"stl":0,"blk":0,"pf":0,"pts":3,"tov":0,"fbpts":0,"fbptsa":0,"fbptsm":0,"pip":0,"pipa":0,"pipm":0,"court":1,"pid":1626242,"pm":-5,"blka":0,"tf":0,"status":"A"},{"fn":"Tim","ln":"Frazier","num":"10","pos":"","min":3,"fga":0,"fgm":0,"tpa":0,"tpm":0,"fta":0,"ftm":0,"oreb":0,"dreb":0,"reb":0,"ast":0,"stl":0,"blk":0,"pf":0,"pts":0,"tov":0,"fbpts":0,"fbptsa":0,"fbptsm":0,"pip":0,"pipa":0,"pipm":0,"court":1,"pid":204025,"pm":-5,"blka":0,"tf":0,"status":"A"},{"fn":"Cliff","ln":"Alexander","num":"34","pos":"","min":0,"fga":0,"fgm":0,"tpa":0,"tpm":0,"fta":0,"ftm":0,"oreb":0,"dreb":0,"reb":0,"ast":0,"stl":0,"blk":0,"pf":0,"pts":0,"tov":0,"fbpts":0,"fbptsa":0,"fbptsm":0,"pip":0,"pipa":0,"pipm":0,"court":0,"pid":1626146,"pm":0,"blka":0,"tf":0,"status":"I"},{"fn":"Gerald","ln":"Henderson","num":" 9","pos":"","min":0,"fga":0,"fgm":0,"tpa":0,"tpm":0,"fta":0,"ftm":0,"oreb":0,"dreb":0,"reb":0,"ast":0,"stl":0,"blk":0,"pf":0,"pts":0,"tov":0,"fbpts":0,"fbptsa":0,"fbptsm":0,"pip":0,"pipa":0,"pipm":0,"court":0,"pid":201945,"pm":0,"blka":0,"tf":0,"status":"I"}],"tn":"Trail Blazers","tc":"Portland","tid":1610612757,"q2":32,"q3":40,"q4":25,"ot1":0,"ot2":0,"ot3":0,"ot4":0,"ot5":0,"ot6":0,"ot7":0,"ot8":0,"ot9":0,"ot10":0},"offs":{"off":[{"fn":"Derrick","ln":"Stafford","num":"9"},{"fn":"Kevin","ln":"Scott","num":"28"},{"fn":"Scott","ln":"Wall","num":"31"}]},"an":"Moda Center","at":19393,"gsts":{"lc":16,"tt":9},"dur":"2:15"}}