{"g":{"mid":1452911069399,"gid":"0021500593","gdte":"2016-01-15","htm":"2016-01-15T19:00:00","vtm":"2016-01-15T19:00:00","etm":"2016-01-15T19:00:00","gdtutc":"2016-01-16","utctm":"00:00","ac":"Indianapolis","as":"IN","gcode":"20160115/WASIND","next":"http://data.nba.com/data/v2015/json/mobile_teams/nba/2015/scores/gamedetail/0021500593_gamedetail.json","ar":0,"p":4,"st":3,"stt":"Final","cl":"00:00.0","lpla":{"evt":537,"cl":"00:00.0","de":"End Period","locX":0,"locY":-80,"opt1":0,"opt2":0,"mtype":0,"etype":13,"opid":"","tid":0,"pid":0,"hs":104,"vs":118,"epid":"","oftid":1610612764},"vls":{"q1":24,"s":118,"ftout":1,"stout":2,"ta":"WAS","tstsg":{"fga":98,"fgm":51,"tpa":25,"tpm":11,"fta":10,"ftm":5,"oreb":17,"dreb":37,"reb":54,"ast":26,"stl":8,"blk":2,"pf":29,"tov":15,"fbpts":17,"fbptsa":10,"fbptsm":8,"pip":46,"pipa":39,"pipm":23,"ble":20,"bpts":67,"tf":0,"scp":14},"pstsg":[{"fn":"Kelly","ln":"Oubre Jr.","num":"12","pos":"F","min":17,"sec":59,"totsec":1079,"fga":6,"fgm":2,"tpa":2,"tpm":1,"fta":4,"ftm":2,"oreb":2,"dreb":2,"reb":4,"ast":0,"stl":2,"blk":0,"pf":3,"pts":7,"tov":0,"fbpts":2,"fbptsa":1,"fbptsm":1,"pip":2,"pipa":3,"pipm":1,"court":1,"pid":1626162,"pm":-2,"blka":1,"tf":0,"status":"A"},{"fn":"Jared","ln":"Dudley","num":" 1","pos":"F","min":30,"sec":4,"totsec":1804,"fga":3,"fgm":1,"tpa":2,"tpm":1,"fta":0,"ftm":0,"oreb":1,"dreb":6,"reb":7,"ast":1,"stl":0,"blk":0,"pf":2,"pts":3,"tov":0,"fbpts":0,"fbptsa":0,"fbptsm":0,"pip":0,"pipa":0,"pipm":0,"court":0,"pid":201162,"pm":14,"blka":0,"tf":0,"status":"A"},{"fn":"","ln":"Nene","num":"42","pos":"C","min":21,"sec":2,"totsec":1262,"fga":9,"fgm":4,"tpa":0,"tpm":0,"fta":0,"ftm":0,"oreb":6,"dreb":2,"reb":8,"ast":2,"stl":1,"blk":1,"pf":5,"pts":8,"tov":4,"fbpts":2,"fbptsa":1,"fbptsm":1,"pip":8,"pipa":6,"pipm":4,"court":0,"pid":2403,"pm":14,"blka":0,"tf":0,"status":"A"},{"fn":"Garrett","ln":"Temple","num":"17","pos":"G","min":28,"sec":14,"totsec":1694,"fga":8,"fgm":2,"tpa":4,"tpm":1,"fta":0,"ftm":0,"oreb":1,"dreb":5,"reb":6,"ast":5,"stl":0,"blk":1,"pf":4,"pts":5,"tov":1,"fbpts":0,"fbptsa":0,"fbptsm":0,"pip":2,"pipa":4,"pipm":1,"court":0,"pid":202066,"pm":15,"blka":2,"tf":0,"status":"A"},{"fn":"John","ln":"Wall","num":" 2","pos":"G","min":31,"sec":23,"totsec":1883,"fga":21,"fgm":12,"tpa":3,"tpm":1,"fta":5,"ftm":3,"oreb":2,"dreb":5,"reb":7,"ast":8,"stl":1,"blk":0,"pf":1,"pts":28,"tov":3,"fbpts":5,"fbptsa":2,"fbptsm":2,"pip":14,"pipa":9,"pipm":7,"court":0,"pid":202322,"pm":7,"blka":0,"tf":0,"status":"A"},{"fn":"Drew","ln":"Gooden","num":"90","pos":"","min":17,"sec":14,"totsec":1034,"fga":9,"fgm":4,"tpa":2,"tpm":0,"fta":0,"ftm":0,"oreb":0,"dreb":4,"reb":4,"ast":0,"stl":0,"blk":0,"pf":3,"pts":8,"tov":2,"fbpts":0,"fbptsa":0,"fbptsm":0,"pip":0,"pipa":1,"pipm":0,"court":0,"pid":2400,"pm":-1,"blka":0,"tf":0,"status":"A"},{"fn":"Bradley","ln":"Beal","num":" 3","pos":"","min":21,"sec":58,"totsec":1318,"fga":15,"fgm":9,"tpa":7,"tpm":4,"fta":1,"ftm":0,"oreb":2,"dreb":3,"reb":5,"ast":1,"stl":0,"blk":0,"pf":3,"pts":22,"tov":2,"fbpts":0,"fbptsa":1,"fbptsm":0,"pip":4,"pipa":4,"pipm":2,"court":0,"pid":203078,"pm":11,"blka":0,"tf":0,"status":"A"},{"fn":"Gary","ln":"Neal","num":"14","pos":"","min":23,"sec":35,"totsec":1415,"fga":10,"fgm":5,"tpa":3,"tpm":2,"fta":0,"ftm":0,"oreb":0,"dreb":4,"reb":4,"ast":3,"stl":0,"blk":0,"pf":2,"pts":12,"tov":1,"fbpts":2,"fbptsa":1,"fbptsm":1,"pip":0,"pipa":1,"pipm":0,"court":1,"pid":202390,"pm":1,"blka":0,"tf":0,"status":"A"},{"fn":"DeJuan","ln":"Blair","num":"45","pos":"","min":22,"sec":49,"totsec":1369,"fga":8,"fgm":6,"tpa":0,"tpm":0,"fta":0,"ftm":0,"oreb":3,"dreb":3,"reb":6,"ast":1,"stl":2,"blk":0,"pf":4,"pts":12,"tov":1,"fbpts":0,"fbptsa":0,"fbptsm":0,"pip":8,"pipa":6,"pipm":4,"court":1,"pid":201971,"pm":7,"blka":0,"tf":0,"status":"A"},{"fn":"Ramon","ln":"Sessions","num":" 7","pos":"","min":23,"sec":2,"totsec":1382,"fga":7,"fgm":5,"tpa":0,"tpm":0,"fta":0,"ftm":0,"oreb":0,"dreb":3,"reb":3,"ast":5,"stl":2,"blk":0,"pf":2,"pts":10,"tov":1,"fbpts":6,"fbptsa":4,"fbptsm":3,"pip":8,"pipa":5,"pipm":4,"court":1,"pid":201196,"pm":10,"blka":0,"tf":0,"status":"A"},{"fn":"Jarell","ln":"Eddie","num":" 8","pos":"","min":2,"sec":40,"totsec":160,"fga":2,"fgm":1,"tpa":2,"tpm":1,"fta":0,"ftm":0,"oreb":0,"dreb":0,"reb":0,"ast":0,"stl":0,"blk":0,"pf":0,"pts":3,"tov":0,"fbpts":0,"fbptsa":0,"fbptsm":0,"pip":0,"pipa":0,"pipm":0,"court":1,"pid":204067,"pm":-6,"blka":0,"tf":0,"status":"A"},{"fn":"Otto","ln":"Porter Jr.","num":"22","pos":"","min":0,"sec":0,"totsec":0,"fga":0,"fgm":0,"tpa":0,"tpm":0,"fta":0,"ftm":0,"oreb":0,"dreb":0,"reb":0,"ast":0,"stl":0,"blk":0,"pf":0,"pts":0,"tov":0,"fbpts":0,"fbptsa":0,"fbptsm":0,"pip":0,"pipa":0,"pipm":0,"court":0,"pid":203490,"pm":0,"blka":0,"tf":0,"status":"A"},{"fn":"Alan","ln":"Anderson","num":" 6","pos":"","min":0,"sec":0,"totsec":0,"fga":0,"fgm":0,"tpa":0,"tpm":0,"fta":0,"ftm":0,"oreb":0,"dreb":0,"reb":0,"ast":0,"stl":0,"blk":0,"pf":0,"pts":0,"tov":0,"fbpts":0,"fbptsa":0,"fbptsm":0,"pip":0,"pipa":0,"pipm":0,"court":0,"pid":101187,"pm":0,"blka":0,"tf":0,"status":"I"},{"fn":"Marcin","ln":"Gortat","num":"13","pos":"","min":0,"sec":0,"totsec":0,"fga":0,"fgm":0,"tpa":0,"tpm":0,"fta":0,"ftm":0,"oreb":0,"dreb":0,"reb":0,"ast":0,"stl":0,"blk":0,"pf":0,"pts":0,"tov":0,"fbpts":0,"fbptsa":0,"fbptsm":0,"pip":0,"pipa":0,"pipm":0,"court":0,"pid":101162,"pm":0,"blka":0,"tf":0,"status":"I"},{"fn":"Kris","ln":"Humphries","num":"43","pos":"","min":0,"sec":0,"totsec":0,"fga":0,"fgm":0,"tpa":0,"tpm":0,"fta":0,"ftm":0,"oreb":0,"dreb":0,"reb":0,"ast":0,"stl":0,"blk":0,"pf":0,"pts":0,"tov":0,"fbpts":0,"fbptsa":0,"fbptsm":0,"pip":0,"pipa":0,"pipm":0,"court":0,"pid":2743,"pm":0,"blka":0,"tf":0,"status":"I"}],"tn":"Wizards","tc":"Washington","tid":1610612764,"q2":35,"q3":29,"q4":30,"ot1":0,"ot2":0,"ot3":0,"ot4":0,"ot5":0,"ot6":0,"ot7":0,"ot8":0,"ot9":0,"ot10":0},"hls":{"q1":27,"s":104,"ftout":1,"stout":0,"ta":"IND","tstsg":{"fga":80,"fgm":38,"tpa":17,"tpm":3,"fta":32,"ftm":25,"oreb":6,"dreb":29,"reb":35,"ast":19,"stl":9,"blk":3,"pf":12,"tov":13,"fbpts":15,"fbptsa":9,"fbptsm":6,"pip":60,"pipa":43,"pipm":30,"ble":3,"bpts":36,"tf":0,"scp":10},"pstsg":[{"fn":"CJ","ln":"Miles","num":" 0","pos":"F","min":26,"sec":35,"totsec":1595,"fga":3,"fgm":1,"tpa":2,"tpm":0,"fta":2,"ftm":2,"oreb":1,"dreb":1,"reb":2,"ast":1,"stl":1,"blk":1,"pf":3,"pts":4,"tov":0,"fbpts":0,"fbptsa":0,"fbptsm":0,"pip":0,"pipa":0,"pipm":0,"court":0,"pid":101139,"pm":-12,"blka":0,"tf":0,"status":"A"},{"fn":"Paul","ln":"George","num":"13","pos":"F","min":33,"sec":49,"totsec":2029,"fga":19,"fgm":6,"tpa":7,"tpm":1,"fta":8,"ftm":8,"oreb":1,"dreb":4,"reb":5,"ast":7,"stl":3,"blk":1,"pf":3,"pts":21,"tov":5,"fbpts":0,"fbptsa":0,"fbptsm":0,"pip":10,"pipa":7,"pipm":5,"court":0,"pid":202331,"pm":-9,"blka":0,"tf":0,"status":"A"},{"fn":"Ian","ln":"Mahinmi","num":"28","pos":"C","min":20,"sec":30,"totsec":1230,"fga":5,"fgm":3,"tpa":0,"tpm":0,"fta":2,"ftm":1,"oreb":0,"dreb":4,"reb":4,"ast":0,"stl":1,"blk":0,"pf":2,"pts":7,"tov":3,"fbpts":0,"fbptsa":0,"fbptsm":0,"pip":6,"pipa":4,"pipm":3,"court":0,"pid":101133,"pm":-7,"blka":1,"tf":0,"status":"A"},{"fn":"Monta","ln":"Ellis","num":"11","pos":"G","min":37,"sec":16,"totsec":2236,"fga":14,"fgm":7,"tpa":2,"tpm":0,"fta":5,"ftm":3,"oreb":0,"dreb":3,"reb":3,"ast":3,"stl":1,"blk":1,"pf":1,"pts":17,"tov":0,"fbpts":5,"fbptsa":4,"fbptsm":2,"pip":12,"pipa":8,"pipm":6,"court":0,"pid":101145,"pm":-7,"blka":0,"tf":0,"status":"A"},{"fn":"George","ln":"Hill","num":" 3","pos":"G","min":33,"sec":39,"totsec":2019,"fga":14,"fgm":8,"tpa":4,"tpm":2,"fta":2,"ftm":1,"oreb":3,"dreb":5,"reb":8,"ast":1,"stl":1,"blk":0,"pf":2,"pts":19,"tov":2,"fbpts":2,"fbptsa":2,"fbptsm":1,"pip":10,"pipa":9,"pipm":5,"court":0,"pid":201588,"pm":-27,"blka":0,"tf":0,"status":"A"},{"fn":"Chase","ln":"Budinger","num":"10","pos":"","min":19,"sec":47,"totsec":1187,"fga":4,"fgm":1,"tpa":2,"tpm":0,"fta":3,"ftm":2,"oreb":0,"dreb":4,"reb":4,"ast":3,"stl":1,"blk":0,"pf":0,"pts":4,"tov":2,"fbpts":4,"fbptsa":1,"fbptsm":1,"pip":2,"pipa":1,"pipm":1,"court":1,"pid":201978,"pm":0,"blka":0,"tf":0,"status":"A"},{"fn":"Lavoy","ln":"Allen","num":" 5","pos":"","min":20,"sec":26,"totsec":1226,"fga":8,"fgm":6,"tpa":0,"tpm":0,"fta":4,"ftm":3,"oreb":0,"dreb":3,"reb":3,"ast":1,"stl":0,"blk":0,"pf":0,"pts":15,"tov":0,"fbpts":0,"fbptsa":0,"fbptsm":0,"pip":10,"pipa":6,"pipm":5,"court":0,"pid":202730,"pm":-2,"blka":0,"tf":0,"status":"A"},{"fn":"Myles","ln":"Turner","num":"33","pos":"","min":18,"sec":15,"totsec":1095,"fga":8,"fgm":4,"tpa":0,"tpm":0,"fta":2,"ftm":2,"oreb":1,"dreb":2,"reb":3,"ast":1,"stl":0,"blk":0,"pf":1,"pts":10,"tov":1,"fbpts":2,"fbptsa":1,"fbptsm":1,"pip":6,"pipa":4,"pipm":3,"court":1,"pid":1626167,"pm":5,"blka":0,"tf":0,"status":"A"},{"fn":"Glenn","ln":"Robinson III","num":"40","pos":"","min":10,"sec":44,"totsec":644,"fga":1,"fgm":0,"tpa":0,"tpm":0,"fta":0,"ftm":0,"oreb":0,"dreb":0,"reb":0,"ast":0,"stl":1,"blk":0,"pf":0,"pts":0,"tov":0,"fbpts":0,"fbptsa":0,"fbptsm":0,"pip":0,"pipa":1,"pipm":0,"court":1,"pid":203922,"pm":-7,"blka":0,"tf":0,"status":"A"},{"fn":"Jordan","ln":"Hill","num":"27","pos":"","min":8,"sec":12,"totsec":492,"fga":2,"fgm":0,"tpa":0,"tpm":0,"fta":2,"ftm":1,"oreb":0,"dreb":2,"reb":2,"ast":2,"stl":0,"blk":0,"pf":0,"pts":1,"tov":0,"fbpts":0,"fbptsa":0,"fbptsm":0,"pip":0,"pipa":1,"pipm":0,"court":0,"pid":201941,"pm":-10,"blka":1,"tf":0,"status":"A"},{"fn":"Solomon","ln":"Hill","num":"44","pos":"","min":7,"sec":34,"totsec":454,"fga":0,"fgm":0,"tpa":0,"tpm":0,"fta":0,"ftm":0,"oreb":0,"dreb":1,"reb":1,"ast":0,"stl":0,"blk":0,"pf":0,"pts":0,"tov":0,"fbpts":0,"fbptsa":0,"fbptsm":0,"pip":0,"pipa":0,"pipm":0,"court":1,"pid":203524,"pm":2,"blka":0,"tf":0,"status":"A"},{"fn":"Joe","ln":"Young","num":" 1","pos":"","min":3,"sec":13,"totsec":193,"fga":2,"fgm":2,"tpa":0,"tpm":0,"fta":2,"ftm":2,"oreb":0,"dreb":0,"reb":0,"ast":0,"stl":0,"blk":0,"pf":0,"pts":6,"tov":0,"fbpts":2,"fbptsa":1,"fbptsm":1,"pip":4,"pipa":2,"pipm":2,"court":1,"pid":1626202,"pm":4,"blka":0,"tf":0,"status":"A"},{"fn":"Rodney","ln":"Stuckey","num":" 2","pos":"","min":0,"sec":0,"totsec":0,"fga":0,"fgm":0,"tpa":0,"tpm":0,"fta":0,"ftm":0,"oreb":0,"dreb":0,"reb":0,"ast":0,"stl":0,"blk":0,"pf":0,"pts":0,"tov":0,"fbpts":0,"fbptsa":0,"fbptsm":0,"pip":0,"pipa":0,"pipm":0,"court":0,"pid":201155,"pm":0,"blka":0,"tf":0,"status":"A"},{"fn":"Rakeem","ln":"Christmas","num":"25","pos":"","min":0,"sec":0,"totsec":0,"fga":0,"fgm":0,"tpa":0,"tpm":0,"fta":0,"ftm":0,"oreb":0,"dreb":0,"reb":0,"ast":0,"stl":0,"blk":0,"pf":0,"pts":0,"tov":0,"fbpts":0,"fbptsa":0,"fbptsm":0,"pip":0,"pipa":0,"pipm":0,"court":0,"pid":1626176,"pm":0,"blka":0,"tf":0,"status":"I"},{"fn":"Shayne","ln":"Whittington","num":"42","pos":"","min":0,"sec":0,"totsec":0,"fga":0,"fgm":0,"tpa":0,"tpm":0,"fta":0,"ftm":0,"oreb":0,"dreb":0,"reb":0,"ast":0,"stl":0,"blk":0,"pf":0,"pts":0,"tov":0,"fbpts":0,"fbptsa":0,"fbptsm":0,"pip":0,"pipa":0,"pipm":0,"court":0,"pid":203963,"pm":0,"blka":0,"tf":0,"status":"I"}],"tn":"Pacers","tc":"Indiana","tid":1610612754,"q2":19,"q3":26,"q4":32,"ot1":0,"ot2":0,"ot3":0,"ot4":0,"ot5":0,"ot6":0,"ot7":0,"ot8":0,"ot9":0,"ot10":0},"offs":{"off":[{"fn":"Michael","ln":"Smith","num":"38"},{"fn":"Nick","ln":"Buchert","num":"3"},{"fn":"Tre","ln":"Maddox","num":"73"}]},"an":"Bankers Life Fieldhouse","at":18165,"gsts":{"lc":4,"tt":3},"dur":"2:10"}}