{"g":{"mid":1449026854876,"gid":"0021500266","gdte":"2015-12-01","htm":"2015-12-01T19:00:00","vtm":"2015-12-01T19:00:00","etm":"2015-12-01T20:00:00","gdtutc":"2015-12-02","utctm":"01:00","ac":"New Orleans","as":"LA","gcode":"20151201/MEMNOP","next":"http://data.nba.com/data/v2015/json/mobile_teams/nba/2015/scores/gamedetail/0021500266_gamedetail.json","ar":0,"p":4,"st":3,"stt":"Final","cl":"00:00.0","lpla":{"evt":574,"cl":"00:00.0","de":"End Period","locX":0,"locY":-80,"opt1":0,"opt2":0,"mtype":0,"etype":13,"opid":"","tid":0,"pid":0,"hs":104,"vs":113,"epid":"","oftid":1610612763},"vls":{"q1":27,"s":113,"ftout":1,"stout":1,"ta":"MEM","tstsg":{"fga":90,"fgm":43,"tpa":10,"tpm":2,"fta":26,"ftm":25,"oreb":13,"dreb":36,"reb":49,"ast":21,"stl":3,"blk":4,"pf":23,"tov":6,"fbpts":12,"fbptsa":7,"fbptsm":4,"pip":52,"pipa":50,"pipm":26,"ble":11,"bpts":41,"tf":0,"scp":15},"pstsg":[{"fn":"Jeff","ln":"Green","num":"32","pos":"F","min":31,"sec":1,"totsec":1861,"fga":11,"fgm":3,"tpa":2,"tpm":0,"fta":0,"ftm":0,"oreb":0,"dreb":4,"reb":4,"ast":1,"stl":1,"blk":0,"pf":3,"pts":6,"tov":0,"fbpts":0,"fbptsa":0,"fbptsm":0,"pip":4,"pipa":7,"pipm":2,"court":1,"pid":201145,"pm":-8,"blka":2,"tf":0,"status":"A"},{"fn":"Zach","ln":"Randolph","num":"50","pos":"F","min":26,"sec":11,"totsec":1571,"fga":14,"fgm":6,"tpa":0,"tpm":0,"fta":2,"ftm":2,"oreb":4,"dreb":2,"reb":6,"ast":0,"stl":0,"blk":0,"pf":2,"pts":14,"tov":0,"fbpts":0,"fbptsa":0,"fbptsm":0,"pip":10,"pipa":11,"pipm":5,"court":1,"pid":2216,"pm":-1,"blka":3,"tf":0,"status":"A"},{"fn":"Marc","ln":"Gasol","num":"33","pos":"C","min":42,"sec":11,"totsec":2531,"fga":22,"fgm":11,"tpa":0,"tpm":0,"fta":16,"ftm":16,"oreb":0,"dreb":13,"reb":13,"ast":6,"stl":0,"blk":4,"pf":1,"pts":38,"tov":3,"fbpts":6,"fbptsa":1,"fbptsm":1,"pip":6,"pipa":9,"pipm":3,"court":1,"pid":201188,"pm":8,"blka":2,"tf":0,"status":"A"},{"fn":"Tony","ln":"Allen","num":" 9","pos":"G","min":14,"sec":53,"totsec":893,"fga":3,"fgm":1,"tpa":1,"tpm":0,"fta":1,"ftm":1,"oreb":2,"dreb":1,"reb":3,"ast":2,"stl":1,"blk":0,"pf":3,"pts":3,"tov":0,"fbpts":0,"fbptsa":0,"fbptsm":0,"pip":2,"pipa":1,"pipm":1,"court":0,"pid":2754,"pm":-6,"blka":0,"tf":0,"status":"A"},{"fn":"Mike","ln":"Conley","num":"11","pos":"G","min":24,"sec":23,"totsec":1463,"fga":10,"fgm":5,"tpa":3,"tpm":1,"fta":0,"ftm":0,"oreb":0,"dreb":2,"reb":2,"ast":3,"stl":0,"blk":0,"pf":0,"pts":11,"tov":2,"fbpts":0,"fbptsa":1,"fbptsm":0,"pip":4,"pipa":3,"pipm":2,"court":1,"pid":201144,"pm":-13,"blka":0,"tf":0,"status":"A"},{"fn":"Courtney","ln":"Lee","num":" 5","pos":"","min":33,"sec":39,"totsec":2019,"fga":12,"fgm":6,"tpa":0,"tpm":0,"fta":1,"ftm":1,"oreb":2,"dreb":2,"reb":4,"ast":1,"stl":1,"blk":0,"pf":3,"pts":13,"tov":1,"fbpts":0,"fbptsa":1,"fbptsm":0,"pip":8,"pipa":7,"pipm":4,"court":1,"pid":201584,"pm":15,"blka":0,"tf":0,"status":"A"},{"fn":"Matt","ln":"Barnes","num":"22","pos":"","min":27,"sec":11,"totsec":1631,"fga":11,"fgm":5,"tpa":4,"tpm":1,"fta":2,"ftm":2,"oreb":1,"dreb":5,"reb":6,"ast":3,"stl":0,"blk":0,"pf":3,"pts":13,"tov":0,"fbpts":6,"fbptsa":4,"fbptsm":3,"pip":8,"pipa":6,"pipm":4,"court":0,"pid":2440,"pm":15,"blka":4,"tf":0,"status":"A"},{"fn":"Mario","ln":"Chalmers","num":" 6","pos":"","min":23,"sec":37,"totsec":1417,"fga":4,"fgm":4,"tpa":0,"tpm":0,"fta":4,"ftm":3,"oreb":1,"dreb":3,"reb":4,"ast":4,"stl":0,"blk":0,"pf":4,"pts":11,"tov":0,"fbpts":0,"fbptsa":0,"fbptsm":0,"pip":6,"pipa":3,"pipm":3,"court":0,"pid":201596,"pm":22,"blka":0,"tf":0,"status":"A"},{"fn":"JaMychal","ln":"Green","num":" 0","pos":"","min":9,"sec":0,"totsec":540,"fga":2,"fgm":1,"tpa":0,"tpm":0,"fta":0,"ftm":0,"oreb":2,"dreb":2,"reb":4,"ast":0,"stl":0,"blk":0,"pf":1,"pts":2,"tov":0,"fbpts":0,"fbptsa":0,"fbptsm":0,"pip":2,"pipa":2,"pipm":1,"court":0,"pid":203210,"pm":11,"blka":0,"tf":0,"status":"A"},{"fn":"Vince","ln":"Carter","num":"15","pos":"","min":7,"sec":53,"totsec":473,"fga":1,"fgm":1,"tpa":0,"tpm":0,"fta":0,"ftm":0,"oreb":1,"dreb":2,"reb":3,"ast":1,"stl":0,"blk":0,"pf":3,"pts":2,"tov":0,"fbpts":0,"fbptsa":0,"fbptsm":0,"pip":2,"pipa":1,"pipm":1,"court":0,"pid":1713,"pm":2,"blka":0,"tf":0,"status":"A"},{"fn":"James","ln":"Ennis","num":" 8","pos":"","min":0,"sec":0,"totsec":0,"fga":0,"fgm":0,"tpa":0,"tpm":0,"fta":0,"ftm":0,"oreb":0,"dreb":0,"reb":0,"ast":0,"stl":0,"blk":0,"pf":0,"pts":0,"tov":0,"fbpts":0,"fbptsa":0,"fbptsm":0,"pip":0,"pipa":0,"pipm":0,"court":0,"pid":203516,"pm":0,"blka":0,"tf":0,"status":"A"},{"fn":"Russ","ln":"Smith","num":" 2","pos":"","min":0,"sec":0,"totsec":0,"fga":0,"fgm":0,"tpa":0,"tpm":0,"fta":0,"ftm":0,"oreb":0,"dreb":0,"reb":0,"ast":0,"stl":0,"blk":0,"pf":0,"pts":0,"tov":0,"fbpts":0,"fbptsa":0,"fbptsm":0,"pip":0,"pipa":0,"pipm":0,"court":0,"pid":203893,"pm":0,"blka":0,"tf":0,"status":"A"},{"fn":"Brandan","ln":"Wright","num":"34","pos":"","min":0,"sec":0,"totsec":0,"fga":0,"fgm":0,"tpa":0,"tpm":0,"fta":0,"ftm":0,"oreb":0,"dreb":0,"reb":0,"ast":0,"stl":0,"blk":0,"pf":0,"pts":0,"tov":0,"fbpts":0,"fbptsa":0,"fbptsm":0,"pip":0,"pipa":0,"pipm":0,"court":0,"pid":201148,"pm":0,"blka":0,"tf":0,"status":"A"},{"fn":"Jordan","ln":"Adams","num":" 3","pos":"","min":0,"sec":0,"totsec":0,"fga":0,"fgm":0,"tpa":0,"tpm":0,"fta":0,"ftm":0,"oreb":0,"dreb":0,"reb":0,"ast":0,"stl":0,"blk":0,"pf":0,"pts":0,"tov":0,"fbpts":0,"fbptsa":0,"fbptsm":0,"pip":0,"pipa":0,"pipm":0,"court":0,"pid":203919,"pm":0,"blka":0,"tf":0,"status":"I"},{"fn":"Jarell","ln":"Martin","num":"10","pos":"","min":0,"sec":0,"totsec":0,"fga":0,"fgm":0,"tpa":0,"tpm":0,"fta":0,"ftm":0,"oreb":0,"dreb":0,"reb":0,"ast":0,"stl":0,"blk":0,"pf":0,"pts":0,"tov":0,"fbpts":0,"fbptsa":0,"fbptsm":0,"pip":0,"pipa":0,"pipm":0,"court":0,"pid":1626185,"pm":0,"blka":0,"tf":0,"status":"I"}],"tn":"Grizzlies","tc":"Memphis","tid":1610612763,"q2":37,"q3":27,"q4":22,"ot1":0,"ot2":0,"ot3":0,"ot4":0,"ot5":0,"ot6":0,"ot7":0,"ot8":0,"ot9":0,"ot10":0},"hls":{"q1":38,"s":104,"ftout":0,"stout":1,"ta":"NOP","tstsg":{"fga":81,"fgm":35,"tpa":27,"tpm":9,"fta":33,"ftm":25,"oreb":9,"dreb":28,"reb":37,"ast":25,"stl":3,"blk":11,"pf":21,"tov":8,"fbpts":8,"fbptsa":6,"fbptsm":3,"pip":42,"pipa":36,"pipm":21,"ble":14,"bpts":39,"tf":1,"scp":13},"pstsg":[{"fn":"Alonzo","ln":"Gee","num":"15","pos":"F","min":28,"sec":16,"totsec":1696,"fga":4,"fgm":3,"tpa":0,"tpm":0,"fta":0,"ftm":0,"oreb":0,"dreb":1,"reb":1,"ast":0,"stl":0,"blk":0,"pf":2,"pts":6,"tov":1,"fbpts":2,"fbptsa":2,"fbptsm":1,"pip":6,"pipa":4,"pipm":3,"court":1,"pid":202087,"pm":5,"blka":0,"tf":0,"status":"A"},{"fn":"Anthony","ln":"Davis","num":"23","pos":"F","min":41,"sec":6,"totsec":2466,"fga":15,"fgm":4,"tpa":1,"tpm":1,"fta":13,"ftm":8,"oreb":3,"dreb":11,"reb":14,"ast":2,"stl":2,"blk":9,"pf":1,"pts":17,"tov":1,"fbpts":0,"fbptsa":0,"fbptsm":0,"pip":4,"pipa":8,"pipm":2,"court":0,"pid":203076,"pm":-1,"blka":1,"tf":0,"status":"A"},{"fn":"Alexis","ln":"Ajinca","num":"42","pos":"C","min":12,"sec":36,"totsec":756,"fga":6,"fgm":5,"tpa":0,"tpm":0,"fta":0,"ftm":0,"oreb":1,"dreb":2,"reb":3,"ast":0,"stl":0,"blk":0,"pf":4,"pts":10,"tov":0,"fbpts":0,"fbptsa":0,"fbptsm":0,"pip":6,"pipa":4,"pipm":3,"court":1,"pid":201582,"pm":9,"blka":0,"tf":0,"status":"A"},{"fn":"Jrue","ln":"Holiday","num":"11","pos":"G","min":25,"sec":58,"totsec":1558,"fga":7,"fgm":4,"tpa":4,"tpm":2,"fta":2,"ftm":2,"oreb":0,"dreb":1,"reb":1,"ast":4,"stl":1,"blk":0,"pf":1,"pts":12,"tov":2,"fbpts":2,"fbptsa":1,"fbptsm":1,"pip":4,"pipa":2,"pipm":2,"court":0,"pid":201950,"pm":6,"blka":0,"tf":0,"status":"A"},{"fn":"Tyreke","ln":"Evans","num":" 1","pos":"G","min":31,"sec":18,"totsec":1878,"fga":12,"fgm":7,"tpa":5,"tpm":2,"fta":4,"ftm":4,"oreb":2,"dreb":3,"reb":5,"ast":10,"stl":0,"blk":1,"pf":0,"pts":20,"tov":1,"fbpts":0,"fbptsa":0,"fbptsm":0,"pip":10,"pipa":6,"pipm":5,"court":0,"pid":201936,"pm":3,"blka":0,"tf":1,"status":"A"},{"fn":"Ryan","ln":"Anderson","num":"33","pos":"","min":33,"sec":27,"totsec":2007,"fga":16,"fgm":6,"tpa":6,"tpm":2,"fta":2,"ftm":2,"oreb":2,"dreb":6,"reb":8,"ast":2,"stl":0,"blk":0,"pf":2,"pts":16,"tov":0,"fbpts":0,"fbptsa":0,"fbptsm":0,"pip":8,"pipa":7,"pipm":4,"court":1,"pid":201583,"pm":-13,"blka":1,"tf":0,"status":"A"},{"fn":"Eric","ln":"Gordon","num":"10","pos":"","min":19,"sec":30,"totsec":1170,"fga":5,"fgm":2,"tpa":3,"tpm":0,"fta":4,"ftm":4,"oreb":0,"dreb":1,"reb":1,"ast":4,"stl":0,"blk":1,"pf":2,"pts":8,"tov":1,"fbpts":0,"fbptsa":1,"fbptsm":0,"pip":2,"pipa":1,"pipm":1,"court":0,"pid":201569,"pm":-20,"blka":0,"tf":0,"status":"A"},{"fn":"Norris","ln":"Cole","num":"30","pos":"","min":22,"sec":43,"totsec":1363,"fga":12,"fgm":3,"tpa":7,"tpm":2,"fta":6,"ftm":3,"oreb":0,"dreb":2,"reb":2,"ast":2,"stl":0,"blk":0,"pf":4,"pts":11,"tov":0,"fbpts":4,"fbptsa":2,"fbptsm":1,"pip":0,"pipa":1,"pipm":0,"court":1,"pid":202708,"pm":-10,"blka":0,"tf":0,"status":"A"},{"fn":"Dante","ln":"Cunningham","num":"44","pos":"","min":5,"sec":37,"totsec":337,"fga":2,"fgm":0,"tpa":1,"tpm":0,"fta":0,"ftm":0,"oreb":1,"dreb":0,"reb":1,"ast":0,"stl":0,"blk":0,"pf":2,"pts":0,"tov":0,"fbpts":0,"fbptsa":0,"fbptsm":0,"pip":0,"pipa":1,"pipm":0,"court":0,"pid":201967,"pm":-4,"blka":1,"tf":0,"status":"A"},{"fn":"Ish","ln":"Smith","num":" 4","pos":"","min":14,"sec":14,"totsec":854,"fga":2,"fgm":1,"tpa":0,"tpm":0,"fta":2,"ftm":2,"oreb":0,"dreb":1,"reb":1,"ast":1,"stl":0,"blk":0,"pf":1,"pts":4,"tov":2,"fbpts":0,"fbptsa":0,"fbptsm":0,"pip":2,"pipa":2,"pipm":1,"court":1,"pid":202397,"pm":-10,"blka":1,"tf":0,"status":"A"},{"fn":"Omer","ln":"Asik","num":" 3","pos":"","min":5,"sec":14,"totsec":314,"fga":0,"fgm":0,"tpa":0,"tpm":0,"fta":0,"ftm":0,"oreb":0,"dreb":0,"reb":0,"ast":0,"stl":0,"blk":0,"pf":2,"pts":0,"tov":0,"fbpts":0,"fbptsa":0,"fbptsm":0,"pip":0,"pipa":0,"pipm":0,"court":0,"pid":201600,"pm":-10,"blka":0,"tf":0,"status":"A"},{"fn":"Luke","ln":"Babbitt","num":" 8","pos":"","min":0,"sec":0,"totsec":0,"fga":0,"fgm":0,"tpa":0,"tpm":0,"fta":0,"ftm":0,"oreb":0,"dreb":0,"reb":0,"ast":0,"stl":0,"blk":0,"pf":0,"pts":0,"tov":0,"fbpts":0,"fbptsa":0,"fbptsm":0,"pip":0,"pipa":0,"pipm":0,"court":0,"pid":202337,"pm":0,"blka":0,"tf":0,"status":"A"},{"fn":"Toney","ln":"Douglas","num":"16","pos":"","min":0,"sec":0,"totsec":0,"fga":0,"fgm":0,"tpa":0,"tpm":0,"fta":0,"ftm":0,"oreb":0,"dreb":0,"reb":0,"ast":0,"stl":0,"blk":0,"pf":0,"pts":0,"tov":0,"fbpts":0,"fbptsa":0,"fbptsm":0,"pip":0,"pipa":0,"pipm":0,"court":0,"pid":201962,"pm":0,"blka":0,"tf":0,"status":"A"},{"fn":"Kendrick","ln":"Perkins","num":" 5","pos":"","min":0,"sec":0,"totsec":0,"fga":0,"fgm":0,"tpa":0,"tpm":0,"fta":0,"ftm":0,"oreb":0,"dreb":0,"reb":0,"ast":0,"stl":0,"blk":0,"pf":0,"pts":0,"tov":0,"fbpts":0,"fbptsa":0,"fbptsm":0,"pip":0,"pipa":0,"pipm":0,"court":0,"pid":2570,"pm":0,"blka":0,"tf":0,"status":"I"},{"fn":"Quincy","ln":"Pondexter","num":"20","pos":"","min":0,"sec":0,"totsec":0,"fga":0,"fgm":0,"tpa":0,"tpm":0,"fta":0,"ftm":0,"oreb":0,"dreb":0,"reb":0,"ast":0,"stl":0,"blk":0,"pf":0,"pts":0,"tov":0,"fbpts":0,"fbptsa":0,"fbptsm":0,"pip":0,"pipa":0,"pipm":0,"court":0,"pid":202347,"pm":0,"blka":0,"tf":0,"status":"I"}],"tn":"Pelicans","tc":"New Orleans","tid":1610612740,"q2":27,"q3":20,"q4":19,"ot1":0,"ot2":0,"ot3":0,"ot4":0,"ot5":0,"ot6":0,"ot7":0,"ot8":0,"ot9":0,"ot10":0},"offs":{"off":[{"fn":"Ed","ln":"Malloy","num":"14"},{"fn":"Mitchell","ln":"Ervin","num":"27"},{"fn":"James","ln":"Williams","num":"60"}]},"an":"Smoothie King Center","at":16020,"gsts":{"lc":7,"tt":5},"dur":"2:16"}}