{"g":{"mid":1480645784049,"gid":"0021600276","gdte":"2016-12-01","htm":"2016-12-01T19:00:00","vtm":"2016-12-01T18:00:00","etm":"2016-12-01T19:00:00","gdtutc":"2016-12-02","utctm":"00:00","ac":"Charlotte","as":"NC","gcode":"20161201/DALCHA","next":"http://data.nba.com/data/v2015/json/mobile_teams/nba/2016/scores/gamedetail/0021600276_gamedetail.json","ar":0,"p":4,"st":3,"stt":"Final","cl":"00:00.0","lpla":{"evt":536,"cl":"00:00.0","de":"End Period","locX":0,"locY":-80,"opt1":0,"opt2":0,"mtype":0,"etype":13,"opid":"","tid":0,"pid":0,"hs":97,"vs":87,"epid":"","oftid":1610612766},"vls":{"q1":14,"s":87,"ftout":0,"stout":0,"ta":"DAL","tstsg":{"fga":86,"fgm":32,"tpa":31,"tpm":9,"fta":18,"ftm":14,"oreb":9,"dreb":32,"reb":41,"ast":18,"stl":6,"blk":2,"pf":25,"tov":11,"fbpts":2,"fbptsa":6,"fbptsm":1,"pip":26,"pipa":29,"pipm":13,"ble":0,"bpts":35,"tf":0,"scp":12,"tmreb":13,"tmtov":2,"potov":11},"pstsg":[{"fn":"Dorian","ln":"Finney-Smith","num":"10","pos":"F","min":25,"sec":1,"totsec":1501,"fga":4,"fgm":1,"tpa":2,"tpm":1,"fta":2,"ftm":1,"oreb":0,"dreb":2,"reb":2,"ast":1,"stl":0,"blk":0,"pf":2,"pts":4,"tov":1,"fbpts":0,"fbptsa":0,"fbptsm":0,"pip":0,"pipa":1,"pipm":0,"court":1,"pid":1627827,"pm":-11,"blka":1,"tf":0,"status":"A","memo":""},{"fn":"Harrison","ln":"Barnes","num":"40","pos":"F","min":37,"sec":41,"totsec":2261,"fga":20,"fgm":8,"tpa":2,"tpm":1,"fta":0,"ftm":0,"oreb":1,"dreb":8,"reb":9,"ast":1,"stl":2,"blk":0,"pf":1,"pts":17,"tov":1,"fbpts":0,"fbptsa":0,"fbptsm":0,"pip":8,"pipa":7,"pipm":4,"court":1,"pid":203084,"pm":-12,"blka":1,"tf":0,"status":"A","memo":""},{"fn":"Salah","ln":"Mejri","num":"50","pos":"C","min":27,"sec":20,"totsec":1640,"fga":4,"fgm":1,"tpa":0,"tpm":0,"fta":2,"ftm":1,"oreb":5,"dreb":6,"reb":11,"ast":0,"stl":1,"blk":1,"pf":5,"pts":3,"tov":2,"fbpts":0,"fbptsa":0,"fbptsm":0,"pip":2,"pipa":3,"pipm":1,"court":1,"pid":1626257,"pm":-13,"blka":1,"tf":0,"status":"A","memo":""},{"fn":"Wesley","ln":"Matthews","num":"23","pos":"G","min":39,"sec":26,"totsec":2366,"fga":15,"fgm":4,"tpa":11,"tpm":1,"fta":5,"ftm":5,"oreb":0,"dreb":3,"reb":3,"ast":2,"stl":0,"blk":0,"pf":2,"pts":14,"tov":1,"fbpts":0,"fbptsa":1,"fbptsm":0,"pip":6,"pipa":4,"pipm":3,"court":1,"pid":202083,"pm":-10,"blka":0,"tf":0,"status":"A","memo":""},{"fn":"Deron","ln":"Williams","num":" 8","pos":"G","min":29,"sec":39,"totsec":1779,"fga":14,"fgm":6,"tpa":7,"tpm":1,"fta":1,"ftm":1,"oreb":0,"dreb":3,"reb":3,"ast":8,"stl":0,"blk":0,"pf":2,"pts":14,"tov":2,"fbpts":0,"fbptsa":1,"fbptsm":0,"pip":0,"pipa":1,"pipm":0,"court":0,"pid":101114,"pm":-1,"blka":1,"tf":0,"status":"A","memo":""},{"fn":"Devin","ln":"Harris","num":"34","pos":"","min":11,"sec":24,"totsec":684,"fga":3,"fgm":1,"tpa":2,"tpm":1,"fta":0,"ftm":0,"oreb":0,"dreb":0,"reb":0,"ast":1,"stl":0,"blk":0,"pf":2,"pts":3,"tov":0,"fbpts":0,"fbptsa":1,"fbptsm":0,"pip":0,"pipa":1,"pipm":0,"court":0,"pid":2734,"pm":0,"blka":0,"tf":0,"status":"A","memo":""},{"fn":"Dwight","ln":"Powell","num":" 7","pos":"","min":24,"sec":16,"totsec":1456,"fga":4,"fgm":2,"tpa":0,"tpm":0,"fta":2,"ftm":2,"oreb":2,"dreb":6,"reb":8,"ast":0,"stl":1,"blk":1,"pf":6,"pts":6,"tov":0,"fbpts":0,"fbptsa":0,"fbptsm":0,"pip":4,"pipa":3,"pipm":2,"court":0,"pid":203939,"pm":0,"blka":0,"tf":0,"status":"A","memo":""},{"fn":"Jonathan","ln":"Gibson","num":" 3","pos":"","min":26,"sec":51,"totsec":1611,"fga":15,"fgm":5,"tpa":4,"tpm":1,"fta":2,"ftm":0,"oreb":0,"dreb":2,"reb":2,"ast":5,"stl":2,"blk":0,"pf":2,"pts":11,"tov":2,"fbpts":0,"fbptsa":1,"fbptsm":0,"pip":4,"pipa":5,"pipm":2,"court":1,"pid":1626780,"pm":-5,"blka":1,"tf":0,"status":"A","memo":""},{"fn":"Justin","ln":"Anderson","num":" 1","pos":"","min":18,"sec":22,"totsec":1102,"fga":7,"fgm":4,"tpa":3,"tpm":3,"fta":4,"ftm":4,"oreb":1,"dreb":2,"reb":3,"ast":0,"stl":0,"blk":0,"pf":3,"pts":15,"tov":2,"fbpts":2,"fbptsa":2,"fbptsm":1,"pip":2,"pipa":4,"pipm":1,"court":0,"pid":1626147,"pm":2,"blka":1,"tf":0,"status":"A","memo":""},{"fn":"Andrew","ln":"Bogut","num":" 6","pos":"","min":0,"sec":0,"totsec":0,"fga":0,"fgm":0,"tpa":0,"tpm":0,"fta":0,"ftm":0,"oreb":0,"dreb":0,"reb":0,"ast":0,"stl":0,"blk":0,"pf":0,"pts":0,"tov":0,"fbpts":0,"fbptsa":0,"fbptsm":0,"pip":0,"pipa":0,"pipm":0,"court":0,"pid":101106,"pm":0,"blka":0,"tf":0,"status":"A","memo":"NWT - Rest"},{"fn":"Nicolas","ln":"Brussino","num":" 9","pos":"","min":0,"sec":0,"totsec":0,"fga":0,"fgm":0,"tpa":0,"tpm":0,"fta":0,"ftm":0,"oreb":0,"dreb":0,"reb":0,"ast":0,"stl":0,"blk":0,"pf":0,"pts":0,"tov":0,"fbpts":0,"fbptsa":0,"fbptsm":0,"pip":0,"pipa":0,"pipm":0,"court":0,"pid":1627852,"pm":0,"blka":0,"tf":0,"status":"A","memo":"DNP - Coach's Decision"},{"fn":"Seth","ln":"Curry","num":"30","pos":"","min":0,"sec":0,"totsec":0,"fga":0,"fgm":0,"tpa":0,"tpm":0,"fta":0,"ftm":0,"oreb":0,"dreb":0,"reb":0,"ast":0,"stl":0,"blk":0,"pf":0,"pts":0,"tov":0,"fbpts":0,"fbptsa":0,"fbptsm":0,"pip":0,"pipa":0,"pipm":0,"court":0,"pid":203552,"pm":0,"blka":0,"tf":0,"status":"A","memo":"DND - Right knee strain"},{"fn":"AJ","ln":"Hammons","num":"20","pos":"","min":0,"sec":0,"totsec":0,"fga":0,"fgm":0,"tpa":0,"tpm":0,"fta":0,"ftm":0,"oreb":0,"dreb":0,"reb":0,"ast":0,"stl":0,"blk":0,"pf":0,"pts":0,"tov":0,"fbpts":0,"fbptsa":0,"fbptsm":0,"pip":0,"pipa":0,"pipm":0,"court":0,"pid":1627773,"pm":0,"blka":0,"tf":0,"status":"A","memo":"DNP - Coach's Decision"},{"fn":"J.J.","ln":"Barea","num":" 5","pos":"","min":0,"sec":0,"totsec":0,"fga":0,"fgm":0,"tpa":0,"tpm":0,"fta":0,"ftm":0,"oreb":0,"dreb":0,"reb":0,"ast":0,"stl":0,"blk":0,"pf":0,"pts":0,"tov":0,"fbpts":0,"fbptsa":0,"fbptsm":0,"pip":0,"pipa":0,"pipm":0,"court":0,"pid":200826,"pm":0,"blka":0,"tf":0,"status":"I","memo":"DNP - Coach's Decision"},{"fn":"Dirk","ln":"Nowitzki","num":"41","pos":"","min":0,"sec":0,"totsec":0,"fga":0,"fgm":0,"tpa":0,"tpm":0,"fta":0,"ftm":0,"oreb":0,"dreb":0,"reb":0,"ast":0,"stl":0,"blk":0,"pf":0,"pts":0,"tov":0,"fbpts":0,"fbptsa":0,"fbptsm":0,"pip":0,"pipa":0,"pipm":0,"court":0,"pid":1717,"pm":0,"blka":0,"tf":0,"status":"I","memo":"DNP - Coach's Decision"}],"tn":"Mavericks","tc":"Dallas","tid":1610612742,"q2":27,"q3":19,"q4":27,"ot1":0,"ot2":0,"ot3":0,"ot4":0,"ot5":0,"ot6":0,"ot7":0,"ot8":0,"ot9":0,"ot10":0},"hls":{"q1":23,"s":97,"ftout":1,"stout":2,"ta":"CHA","tstsg":{"fga":74,"fgm":35,"tpa":18,"tpm":5,"fta":31,"ftm":22,"oreb":4,"dreb":35,"reb":39,"ast":24,"stl":5,"blk":6,"pf":18,"tov":10,"fbpts":6,"fbptsa":2,"fbptsm":1,"pip":40,"pipa":34,"pipm":20,"ble":11,"bpts":46,"tf":2,"scp":6,"tmreb":13,"tmtov":0,"potov":11},"pstsg":[{"fn":"Michael","ln":"Kidd-Gilchrist","num":"14","pos":"F","min":33,"sec":8,"totsec":1988,"fga":9,"fgm":4,"tpa":0,"tpm":0,"fta":8,"ftm":6,"oreb":1,"dreb":2,"reb":3,"ast":2,"stl":0,"blk":1,"pf":3,"pts":14,"tov":1,"fbpts":3,"fbptsa":1,"fbptsm":1,"pip":4,"pipa":3,"pipm":2,"court":1,"pid":203077,"pm":8,"blka":0,"tf":0,"status":"A","memo":""},{"fn":"Frank","ln":"Kaminsky","num":"44","pos":"F","min":22,"sec":5,"totsec":1325,"fga":4,"fgm":0,"tpa":0,"tpm":0,"fta":2,"ftm":1,"oreb":1,"dreb":2,"reb":3,"ast":0,"stl":1,"blk":0,"pf":2,"pts":1,"tov":0,"fbpts":0,"fbptsa":0,"fbptsm":0,"pip":0,"pipa":3,"pipm":0,"court":0,"pid":1626163,"pm":7,"blka":0,"tf":0,"status":"A","memo":""},{"fn":"Cody","ln":"Zeller","num":"40","pos":"C","min":30,"sec":45,"totsec":1845,"fga":5,"fgm":3,"tpa":0,"tpm":0,"fta":0,"ftm":0,"oreb":1,"dreb":6,"reb":7,"ast":1,"stl":0,"blk":1,"pf":2,"pts":6,"tov":0,"fbpts":0,"fbptsa":0,"fbptsm":0,"pip":6,"pipa":5,"pipm":3,"court":1,"pid":203469,"pm":2,"blka":1,"tf":1,"status":"A","memo":""},{"fn":"Nicolas","ln":"Batum","num":" 5","pos":"G","min":36,"sec":29,"totsec":2189,"fga":12,"fgm":4,"tpa":5,"tpm":1,"fta":4,"ftm":3,"oreb":0,"dreb":9,"reb":9,"ast":6,"stl":1,"blk":0,"pf":1,"pts":12,"tov":3,"fbpts":0,"fbptsa":0,"fbptsm":0,"pip":2,"pipa":2,"pipm":1,"court":1,"pid":201587,"pm":10,"blka":0,"tf":0,"status":"A","memo":""},{"fn":"Kemba","ln":"Walker","num":"15","pos":"G","min":32,"sec":35,"totsec":1955,"fga":19,"fgm":7,"tpa":10,"tpm":3,"fta":2,"ftm":1,"oreb":0,"dreb":3,"reb":3,"ast":5,"stl":1,"blk":0,"pf":4,"pts":18,"tov":3,"fbpts":1,"fbptsa":1,"fbptsm":0,"pip":4,"pipa":5,"pipm":2,"court":1,"pid":202689,"pm":3,"blka":1,"tf":0,"status":"A","memo":""},{"fn":"Marco","ln":"Belinelli","num":"21","pos":"","min":20,"sec":16,"totsec":1216,"fga":5,"fgm":3,"tpa":1,"tpm":0,"fta":2,"ftm":2,"oreb":0,"dreb":1,"reb":1,"ast":2,"stl":1,"blk":0,"pf":0,"pts":8,"tov":0,"fbpts":0,"fbptsa":0,"fbptsm":0,"pip":2,"pipa":1,"pipm":1,"court":0,"pid":201158,"pm":5,"blka":0,"tf":0,"status":"A","memo":""},{"fn":"Ramon","ln":"Sessions","num":" 7","pos":"","min":15,"sec":25,"totsec":925,"fga":3,"fgm":3,"tpa":0,"tpm":0,"fta":2,"ftm":2,"oreb":0,"dreb":0,"reb":0,"ast":3,"stl":0,"blk":0,"pf":1,"pts":8,"tov":0,"fbpts":2,"fbptsa":0,"fbptsm":0,"pip":4,"pipa":2,"pipm":2,"court":0,"pid":201196,"pm":7,"blka":0,"tf":0,"status":"A","memo":""},{"fn":"Roy","ln":"Hibbert","num":"55","pos":"","min":17,"sec":15,"totsec":1035,"fga":7,"fgm":5,"tpa":0,"tpm":0,"fta":5,"ftm":1,"oreb":0,"dreb":4,"reb":4,"ast":2,"stl":0,"blk":2,"pf":3,"pts":11,"tov":0,"fbpts":0,"fbptsa":0,"fbptsm":0,"pip":10,"pipa":7,"pipm":5,"court":0,"pid":201579,"pm":8,"blka":0,"tf":1,"status":"A","memo":""},{"fn":"Spencer","ln":"Hawes","num":"00","pos":"","min":13,"sec":3,"totsec":783,"fga":3,"fgm":3,"tpa":0,"tpm":0,"fta":1,"ftm":1,"oreb":0,"dreb":3,"reb":3,"ast":1,"stl":1,"blk":1,"pf":1,"pts":7,"tov":0,"fbpts":0,"fbptsa":0,"fbptsm":0,"pip":4,"pipa":2,"pipm":2,"court":0,"pid":201150,"pm":-1,"blka":0,"tf":0,"status":"A","memo":""},{"fn":"Jeremy","ln":"Lamb","num":" 3","pos":"","min":18,"sec":59,"totsec":1139,"fga":7,"fgm":3,"tpa":2,"tpm":1,"fta":5,"ftm":5,"oreb":1,"dreb":5,"reb":6,"ast":2,"stl":0,"blk":1,"pf":1,"pts":12,"tov":3,"fbpts":0,"fbptsa":0,"fbptsm":0,"pip":4,"pipa":4,"pipm":2,"court":1,"pid":203087,"pm":1,"blka":0,"tf":0,"status":"A","memo":""},{"fn":"Treveon","ln":"Graham","num":"12","pos":"","min":0,"sec":0,"totsec":0,"fga":0,"fgm":0,"tpa":0,"tpm":0,"fta":0,"ftm":0,"oreb":0,"dreb":0,"reb":0,"ast":0,"stl":0,"blk":0,"pf":0,"pts":0,"tov":0,"fbpts":0,"fbptsa":0,"fbptsm":0,"pip":0,"pipa":0,"pipm":0,"court":0,"pid":1626203,"pm":0,"blka":0,"tf":0,"status":"A","memo":"DNP - Coach's Decision"},{"fn":"Aaron","ln":"Harrison","num":" 9","pos":"","min":0,"sec":0,"totsec":0,"fga":0,"fgm":0,"tpa":0,"tpm":0,"fta":0,"ftm":0,"oreb":0,"dreb":0,"reb":0,"ast":0,"stl":0,"blk":0,"pf":0,"pts":0,"tov":0,"fbpts":0,"fbptsa":0,"fbptsm":0,"pip":0,"pipa":0,"pipm":0,"court":0,"pid":1626151,"pm":0,"blka":0,"tf":0,"status":"A","memo":"DNP - Coach's Decision"},{"fn":"Brian","ln":"Roberts","num":"22","pos":"","min":0,"sec":0,"totsec":0,"fga":0,"fgm":0,"tpa":0,"tpm":0,"fta":0,"ftm":0,"oreb":0,"dreb":0,"reb":0,"ast":0,"stl":0,"blk":0,"pf":0,"pts":0,"tov":0,"fbpts":0,"fbptsa":0,"fbptsm":0,"pip":0,"pipa":0,"pipm":0,"court":0,"pid":203148,"pm":0,"blka":0,"tf":0,"status":"A","memo":"DNP - Coach's Decision"},{"fn":"Marvin","ln":"Williams","num":" 2","pos":"","min":0,"sec":0,"totsec":0,"fga":0,"fgm":0,"tpa":0,"tpm":0,"fta":0,"ftm":0,"oreb":0,"dreb":0,"reb":0,"ast":0,"stl":0,"blk":0,"pf":0,"pts":0,"tov":0,"fbpts":0,"fbptsa":0,"fbptsm":0,"pip":0,"pipa":0,"pipm":0,"court":0,"pid":101107,"pm":0,"blka":0,"tf":0,"status":"I","memo":"DNP - Coach's Decision"},{"fn":"Christian","ln":"Wood","num":"35","pos":"","min":0,"sec":0,"totsec":0,"fga":0,"fgm":0,"tpa":0,"tpm":0,"fta":0,"ftm":0,"oreb":0,"dreb":0,"reb":0,"ast":0,"stl":0,"blk":0,"pf":0,"pts":0,"tov":0,"fbpts":0,"fbptsa":0,"fbptsm":0,"pip":0,"pipa":0,"pipm":0,"court":0,"pid":1626174,"pm":0,"blka":0,"tf":0,"status":"I","memo":"DNP - Coach's Decision"}],"tn":"Hornets","tc":"Charlotte","tid":1610612766,"q2":21,"q3":24,"q4":29,"ot1":0,"ot2":0,"ot3":0,"ot4":0,"ot5":0,"ot6":0,"ot7":0,"ot8":0,"ot9":0,"ot10":0},"ldrs":{"vis":{"ptsl":{"val":17,"ldr":[{"ln":"Barnes","fn":"Harrison","pcd":"harrison_barnes","pid":203084}]},"astl":{"val":8,"ldr":[{"ln":"Williams","fn":"Deron","pcd":"deron_williams","pid":101114}]},"rebl":{"val":11,"ldr":[{"ln":"Mejri","fn":"Salah","pcd":"salah_mejri","pid":1626257}]}},"home":{"ptsl":{"val":18,"ldr":[{"ln":"Walker","fn":"Kemba","pcd":"kemba_walker","pid":202689}]},"astl":{"val":6,"ldr":[{"ln":"Batum","fn":"Nicolas","pcd":"nicolas_batum","pid":201587}]},"rebl":{"val":9,"ldr":[{"ln":"Batum","fn":"Nicolas","pcd":"nicolas_batum","pid":201587}]}}},"offs":{"off":[{"fn":"Kane","ln":"Fitzgerald","num":"5"},{"fn":"Karl","ln":"Lane","num":"77"},{"fn":"James","ln":"Williams","num":"60"}]},"an":"Time Warner Cable Arena","at":14471,"gsts":{"lc":0,"tt":1},"dur":"2:19"}}