{"g":{"mid":1483480539240,"gid":"0021600087","gdte":"2016-11-06","htm":"2016-11-06T12:00:00","vtm":"2016-11-06T10:00:00","etm":"2016-11-06T12:00:00","gdtutc":"2016-11-06","utctm":"17:00","ac":"New York","as":"NY","gcode":"20161106/UTANYK","next":"http://data.nba.com/data/v2015/json/mobile_teams/nba/2016/scores/gamedetail/0021600087_gamedetail.json","ar":0,"p":4,"st":3,"stt":"Final","cl":"00:00.0","lpla":{"evt":540,"cl":"00:00.0","de":"End Period","locX":0,"locY":-80,"opt1":0,"opt2":0,"mtype":0,"etype":13,"opid":"","tid":0,"pid":0,"hs":109,"vs":114,"epid":"","oftid":1610612762},"vls":{"q1":20,"s":114,"ftout":1,"stout":0,"ta":"UTA","tstsg":{"fga":75,"fgm":38,"tpa":25,"tpm":8,"fta":35,"ftm":30,"oreb":7,"dreb":27,"reb":34,"ast":21,"stl":6,"blk":4,"pf":19,"tov":10,"fbpts":6,"fbptsa":4,"fbptsm":3,"pip":42,"pipa":32,"pipm":21,"ble":9,"bpts":19,"tf":0,"scp":11,"tmreb":7,"tmtov":1,"potov":13},"pstsg":[{"fn":"Derrick","ln":"Favors","num":"15","pos":"F","min":27,"sec":1,"totsec":1621,"fga":10,"fgm":6,"tpa":0,"tpm":0,"fta":3,"ftm":1,"oreb":3,"dreb":3,"reb":6,"ast":0,"stl":0,"blk":0,"pf":5,"pts":13,"tov":2,"fbpts":0,"fbptsa":0,"fbptsm":0,"pip":8,"pipa":6,"pipm":4,"court":1,"pid":202324,"pm":-5,"blka":3,"tf":0,"status":"A","memo":""},{"fn":"Gordon","ln":"Hayward","num":"20","pos":"F","min":35,"sec":33,"totsec":2133,"fga":17,"fgm":6,"tpa":8,"tpm":2,"fta":14,"ftm":14,"oreb":1,"dreb":4,"reb":5,"ast":0,"stl":0,"blk":0,"pf":3,"pts":28,"tov":3,"fbpts":4,"fbptsa":2,"fbptsm":2,"pip":4,"pipa":5,"pipm":2,"court":1,"pid":202330,"pm":7,"blka":0,"tf":0,"status":"A","memo":""},{"fn":"Rudy","ln":"Gobert","num":"27","pos":"C","min":33,"sec":23,"totsec":2003,"fga":6,"fgm":5,"tpa":0,"tpm":0,"fta":4,"ftm":3,"oreb":2,"dreb":6,"reb":8,"ast":1,"stl":1,"blk":3,"pf":6,"pts":13,"tov":0,"fbpts":2,"fbptsa":1,"fbptsm":1,"pip":10,"pipa":6,"pipm":5,"court":0,"pid":203497,"pm":11,"blka":1,"tf":0,"status":"A","memo":""},{"fn":"Rodney","ln":"Hood","num":" 5","pos":"G","min":38,"sec":17,"totsec":2297,"fga":13,"fgm":7,"tpa":4,"tpm":2,"fta":3,"ftm":2,"oreb":0,"dreb":6,"reb":6,"ast":5,"stl":1,"blk":0,"pf":2,"pts":18,"tov":0,"fbpts":0,"fbptsa":0,"fbptsm":0,"pip":6,"pipa":5,"pipm":3,"court":1,"pid":203918,"pm":11,"blka":0,"tf":0,"status":"A","memo":""},{"fn":"George","ln":"Hill","num":" 3","pos":"G","min":34,"sec":36,"totsec":2076,"fga":12,"fgm":8,"tpa":3,"tpm":1,"fta":7,"ftm":6,"oreb":0,"dreb":2,"reb":2,"ast":8,"stl":2,"blk":0,"pf":1,"pts":23,"tov":0,"fbpts":0,"fbptsa":1,"fbptsm":0,"pip":10,"pipa":6,"pipm":5,"court":1,"pid":201588,"pm":2,"blka":0,"tf":0,"status":"A","memo":""},{"fn":"Dante","ln":"Exum","num":"11","pos":"","min":10,"sec":41,"totsec":641,"fga":1,"fgm":0,"tpa":1,"tpm":0,"fta":0,"ftm":0,"oreb":0,"dreb":0,"reb":0,"ast":2,"stl":0,"blk":0,"pf":0,"pts":0,"tov":0,"fbpts":0,"fbptsa":0,"fbptsm":0,"pip":0,"pipa":0,"pipm":0,"court":0,"pid":203957,"pm":-5,"blka":0,"tf":0,"status":"A","memo":""},{"fn":"Trey","ln":"Lyles","num":"41","pos":"","min":20,"sec":37,"totsec":1237,"fga":6,"fgm":2,"tpa":4,"tpm":1,"fta":0,"ftm":0,"oreb":0,"dreb":2,"reb":2,"ast":1,"stl":0,"blk":1,"pf":0,"pts":5,"tov":0,"fbpts":0,"fbptsa":0,"fbptsm":0,"pip":0,"pipa":0,"pipm":0,"court":0,"pid":1626168,"pm":-4,"blka":0,"tf":0,"status":"A","memo":""},{"fn":"Joe","ln":"Johnson","num":" 6","pos":"","min":23,"sec":44,"totsec":1424,"fga":6,"fgm":2,"tpa":4,"tpm":2,"fta":4,"ftm":4,"oreb":1,"dreb":1,"reb":2,"ast":2,"stl":2,"blk":0,"pf":2,"pts":10,"tov":1,"fbpts":0,"fbptsa":0,"fbptsm":0,"pip":0,"pipa":1,"pipm":0,"court":1,"pid":2207,"pm":8,"blka":1,"tf":0,"status":"A","memo":""},{"fn":"Shelvin","ln":"Mack","num":" 8","pos":"","min":12,"sec":26,"totsec":746,"fga":3,"fgm":2,"tpa":0,"tpm":0,"fta":0,"ftm":0,"oreb":0,"dreb":3,"reb":3,"ast":2,"stl":0,"blk":0,"pf":0,"pts":4,"tov":4,"fbpts":0,"fbptsa":0,"fbptsm":0,"pip":4,"pipa":3,"pipm":2,"court":0,"pid":202714,"pm":2,"blka":0,"tf":0,"status":"A","memo":""},{"fn":"Joe","ln":"Ingles","num":" 2","pos":"","min":3,"sec":42,"totsec":222,"fga":1,"fgm":0,"tpa":1,"tpm":0,"fta":0,"ftm":0,"oreb":0,"dreb":0,"reb":0,"ast":0,"stl":0,"blk":0,"pf":0,"pts":0,"tov":0,"fbpts":0,"fbptsa":0,"fbptsm":0,"pip":0,"pipa":0,"pipm":0,"court":0,"pid":204060,"pm":-2,"blka":0,"tf":0,"status":"A","memo":""},{"fn":"Joel","ln":"Bolomboy","num":"21","pos":"","min":0,"sec":0,"totsec":0,"fga":0,"fgm":0,"tpa":0,"tpm":0,"fta":0,"ftm":0,"oreb":0,"dreb":0,"reb":0,"ast":0,"stl":0,"blk":0,"pf":0,"pts":0,"tov":0,"fbpts":0,"fbptsa":0,"fbptsm":0,"pip":0,"pipa":0,"pipm":0,"court":0,"pid":1627762,"pm":0,"blka":0,"tf":0,"status":"A","memo":"DNP - Coach's Decision"},{"fn":"Raul","ln":"Neto","num":"25","pos":"","min":0,"sec":0,"totsec":0,"fga":0,"fgm":0,"tpa":0,"tpm":0,"fta":0,"ftm":0,"oreb":0,"dreb":0,"reb":0,"ast":0,"stl":0,"blk":0,"pf":0,"pts":0,"tov":0,"fbpts":0,"fbptsa":0,"fbptsm":0,"pip":0,"pipa":0,"pipm":0,"court":0,"pid":203526,"pm":0,"blka":0,"tf":0,"status":"A","memo":"DNP - Coach's Decision"},{"fn":"Jeff","ln":"Withey","num":"24","pos":"","min":0,"sec":0,"totsec":0,"fga":0,"fgm":0,"tpa":0,"tpm":0,"fta":0,"ftm":0,"oreb":0,"dreb":0,"reb":0,"ast":0,"stl":0,"blk":0,"pf":0,"pts":0,"tov":0,"fbpts":0,"fbptsa":0,"fbptsm":0,"pip":0,"pipa":0,"pipm":0,"court":0,"pid":203481,"pm":0,"blka":0,"tf":0,"status":"A","memo":"DNP - Coach's Decision"},{"fn":"Alec","ln":"Burks","num":"10","pos":"","min":0,"sec":0,"totsec":0,"fga":0,"fgm":0,"tpa":0,"tpm":0,"fta":0,"ftm":0,"oreb":0,"dreb":0,"reb":0,"ast":0,"stl":0,"blk":0,"pf":0,"pts":0,"tov":0,"fbpts":0,"fbptsa":0,"fbptsm":0,"pip":0,"pipa":0,"pipm":0,"court":0,"pid":202692,"pm":0,"blka":0,"tf":0,"status":"I","memo":""},{"fn":"Boris","ln":"Diaw","num":"33","pos":"","min":0,"sec":0,"totsec":0,"fga":0,"fgm":0,"tpa":0,"tpm":0,"fta":0,"ftm":0,"oreb":0,"dreb":0,"reb":0,"ast":0,"stl":0,"blk":0,"pf":0,"pts":0,"tov":0,"fbpts":0,"fbptsa":0,"fbptsm":0,"pip":0,"pipa":0,"pipm":0,"court":0,"pid":2564,"pm":0,"blka":0,"tf":0,"status":"I","memo":""}],"tn":"Jazz","tc":"Utah","tid":1610612762,"q2":29,"q3":29,"q4":36,"ot1":0,"ot2":0,"ot3":0,"ot4":0,"ot5":0,"ot6":0,"ot7":0,"ot8":0,"ot9":0,"ot10":0},"hls":{"q1":30,"s":109,"ftout":0,"stout":0,"ta":"NYK","tstsg":{"fga":83,"fgm":42,"tpa":20,"tpm":8,"fta":19,"ftm":17,"oreb":10,"dreb":29,"reb":39,"ast":18,"stl":8,"blk":5,"pf":26,"tov":12,"fbpts":11,"fbptsa":8,"fbptsm":4,"pip":38,"pipa":41,"pipm":19,"ble":13,"bpts":21,"tf":0,"scp":13,"tmreb":5,"tmtov":1,"potov":9},"pstsg":[{"fn":"Carmelo","ln":"Anthony","num":" 7","pos":"F","min":35,"sec":28,"totsec":2128,"fga":20,"fgm":12,"tpa":6,"tpm":0,"fta":6,"ftm":4,"oreb":1,"dreb":8,"reb":9,"ast":3,"stl":0,"blk":0,"pf":5,"pts":28,"tov":1,"fbpts":0,"fbptsa":1,"fbptsm":0,"pip":8,"pipa":6,"pipm":4,"court":1,"pid":2546,"pm":6,"blka":0,"tf":0,"status":"A","memo":""},{"fn":"Kristaps","ln":"Porzingis","num":" 6","pos":"F","min":33,"sec":21,"totsec":2001,"fga":18,"fgm":10,"tpa":7,"tpm":3,"fta":5,"ftm":5,"oreb":1,"dreb":7,"reb":8,"ast":1,"stl":0,"blk":2,"pf":4,"pts":28,"tov":2,"fbpts":5,"fbptsa":2,"fbptsm":2,"pip":8,"pipa":7,"pipm":4,"court":1,"pid":204001,"pm":0,"blka":1,"tf":0,"status":"A","memo":""},{"fn":"Joakim","ln":"Noah","num":"13","pos":"C","min":20,"sec":2,"totsec":1202,"fga":3,"fgm":2,"tpa":0,"tpm":0,"fta":0,"ftm":0,"oreb":2,"dreb":3,"reb":5,"ast":2,"stl":1,"blk":1,"pf":3,"pts":4,"tov":2,"fbpts":0,"fbptsa":0,"fbptsm":0,"pip":4,"pipa":3,"pipm":2,"court":0,"pid":201149,"pm":1,"blka":1,"tf":0,"status":"A","memo":""},{"fn":"Courtney","ln":"Lee","num":" 5","pos":"G","min":36,"sec":27,"totsec":2187,"fga":8,"fgm":3,"tpa":2,"tpm":2,"fta":2,"ftm":2,"oreb":1,"dreb":5,"reb":6,"ast":0,"stl":3,"blk":0,"pf":3,"pts":10,"tov":2,"fbpts":0,"fbptsa":1,"fbptsm":0,"pip":2,"pipa":4,"pipm":1,"court":1,"pid":201584,"pm":4,"blka":0,"tf":0,"status":"A","memo":""},{"fn":"Derrick","ln":"Rose","num":"25","pos":"G","min":36,"sec":11,"totsec":2171,"fga":14,"fgm":7,"tpa":0,"tpm":0,"fta":4,"ftm":4,"oreb":2,"dreb":2,"reb":4,"ast":8,"stl":1,"blk":0,"pf":3,"pts":18,"tov":4,"fbpts":4,"fbptsa":2,"fbptsm":2,"pip":10,"pipa":11,"pipm":5,"court":1,"pid":201565,"pm":1,"blka":1,"tf":0,"status":"A","memo":""},{"fn":"Lance","ln":"Thomas","num":"42","pos":"","min":29,"sec":5,"totsec":1745,"fga":5,"fgm":2,"tpa":1,"tpm":1,"fta":0,"ftm":0,"oreb":0,"dreb":2,"reb":2,"ast":1,"stl":1,"blk":0,"pf":4,"pts":5,"tov":0,"fbpts":0,"fbptsa":0,"fbptsm":0,"pip":2,"pipa":3,"pipm":1,"court":0,"pid":202498,"pm":-9,"blka":1,"tf":0,"status":"A","memo":""},{"fn":"Kyle","ln":"O'Quinn","num":" 9","pos":"","min":12,"sec":40,"totsec":760,"fga":4,"fgm":1,"tpa":0,"tpm":0,"fta":2,"ftm":2,"oreb":1,"dreb":0,"reb":1,"ast":0,"stl":0,"blk":2,"pf":1,"pts":4,"tov":0,"fbpts":2,"fbptsa":0,"fbptsm":0,"pip":2,"pipa":2,"pipm":1,"court":0,"pid":203124,"pm":-7,"blka":0,"tf":0,"status":"A","memo":""},{"fn":"Brandon","ln":"Jennings","num":" 3","pos":"","min":15,"sec":55,"totsec":955,"fga":4,"fgm":2,"tpa":2,"tpm":1,"fta":0,"ftm":0,"oreb":0,"dreb":1,"reb":1,"ast":2,"stl":2,"blk":0,"pf":2,"pts":5,"tov":1,"fbpts":0,"fbptsa":0,"fbptsm":0,"pip":0,"pipa":1,"pipm":0,"court":1,"pid":201943,"pm":-5,"blka":0,"tf":0,"status":"A","memo":""},{"fn":"Justin","ln":"Holiday","num":" 8","pos":"","min":13,"sec":1,"totsec":781,"fga":2,"fgm":1,"tpa":0,"tpm":0,"fta":0,"ftm":0,"oreb":0,"dreb":1,"reb":1,"ast":1,"stl":0,"blk":0,"pf":0,"pts":2,"tov":0,"fbpts":0,"fbptsa":1,"fbptsm":0,"pip":0,"pipa":1,"pipm":0,"court":0,"pid":203200,"pm":-10,"blka":0,"tf":0,"status":"A","memo":""},{"fn":"Mindaugas","ln":"Kuzminskas","num":"91","pos":"","min":7,"sec":49,"totsec":469,"fga":5,"fgm":2,"tpa":2,"tpm":1,"fta":0,"ftm":0,"oreb":2,"dreb":0,"reb":2,"ast":0,"stl":0,"blk":0,"pf":1,"pts":5,"tov":0,"fbpts":0,"fbptsa":1,"fbptsm":0,"pip":2,"pipa":3,"pipm":1,"court":0,"pid":1627851,"pm":-6,"blka":0,"tf":0,"status":"A","memo":""},{"fn":"Ron","ln":"Baker","num":"31","pos":"","min":0,"sec":0,"totsec":0,"fga":0,"fgm":0,"tpa":0,"tpm":0,"fta":0,"ftm":0,"oreb":0,"dreb":0,"reb":0,"ast":0,"stl":0,"blk":0,"pf":0,"pts":0,"tov":0,"fbpts":0,"fbptsa":0,"fbptsm":0,"pip":0,"pipa":0,"pipm":0,"court":0,"pid":1627758,"pm":0,"blka":0,"tf":0,"status":"A","memo":"DNP - Coach's Decision"},{"fn":"Willy","ln":"Hernangomez","num":"14","pos":"","min":0,"sec":0,"totsec":0,"fga":0,"fgm":0,"tpa":0,"tpm":0,"fta":0,"ftm":0,"oreb":0,"dreb":0,"reb":0,"ast":0,"stl":0,"blk":0,"pf":0,"pts":0,"tov":0,"fbpts":0,"fbptsa":0,"fbptsm":0,"pip":0,"pipa":0,"pipm":0,"court":0,"pid":1626195,"pm":0,"blka":0,"tf":0,"status":"A","memo":"DNP - Coach's Decision"},{"fn":"Sasha","ln":"Vujacic","num":"18","pos":"","min":0,"sec":0,"totsec":0,"fga":0,"fgm":0,"tpa":0,"tpm":0,"fta":0,"ftm":0,"oreb":0,"dreb":0,"reb":0,"ast":0,"stl":0,"blk":0,"pf":0,"pts":0,"tov":0,"fbpts":0,"fbptsa":0,"fbptsm":0,"pip":0,"pipa":0,"pipm":0,"court":0,"pid":2756,"pm":0,"blka":0,"tf":0,"status":"A","memo":"DNP - Coach's Decision"},{"fn":"Maurice","ln":"Ndour","num":" 2","pos":"","min":0,"sec":0,"totsec":0,"fga":0,"fgm":0,"tpa":0,"tpm":0,"fta":0,"ftm":0,"oreb":0,"dreb":0,"reb":0,"ast":0,"stl":0,"blk":0,"pf":0,"pts":0,"tov":0,"fbpts":0,"fbptsa":0,"fbptsm":0,"pip":0,"pipa":0,"pipm":0,"court":0,"pid":1626254,"pm":0,"blka":0,"tf":0,"status":"I","memo":""},{"fn":"Marshall","ln":"Plumlee","num":"40","pos":"","min":0,"sec":0,"totsec":0,"fga":0,"fgm":0,"tpa":0,"tpm":0,"fta":0,"ftm":0,"oreb":0,"dreb":0,"reb":0,"ast":0,"stl":0,"blk":0,"pf":0,"pts":0,"tov":0,"fbpts":0,"fbptsa":0,"fbptsm":0,"pip":0,"pipa":0,"pipm":0,"court":0,"pid":1627850,"pm":0,"blka":0,"tf":0,"status":"I","memo":""}],"tn":"Knicks","tc":"New York","tid":1610612752,"q2":24,"q3":26,"q4":29,"ot1":0,"ot2":0,"ot3":0,"ot4":0,"ot5":0,"ot6":0,"ot7":0,"ot8":0,"ot9":0,"ot10":0},"offs":{"off":[{"fn":"Scott","ln":"Foster","num":"48"},{"fn":"Matt","ln":"Boland","num":"18"},{"fn":"Curtis","ln":"Blair","num":"74"}]},"an":"Madison Square Garden","at":19812,"gsts":{"lc":6,"tt":5},"dur":"2:19"}}