{"g":{"mid":1515009593399,"gid":"0021700546","gdte":"2018-01-01","htm":"2018-01-01T19:30:00","vtm":"2018-01-01T18:30:00","etm":"2018-01-01T19:30:00","gdtutc":"2018-01-02","utctm":"00:30","ac":"Toronto","as":"ON","gcode":"20180101/MILTOR","next":"http://data.nba.com/data/v2015/json/mobile_teams/nba/2017/scores/gamedetail/0021700546_gamedetail.json","ar":0,"p":5,"st":3,"stt":"Final","cl":"00:00.0","lpla":{"evt":681,"cl":"00:00.0","de":"End Period","locX":0,"locY":-80,"opt1":0,"opt2":0,"mtype":0,"etype":13,"opid":"","tid":0,"pid":0,"hs":131,"vs":127,"epid":"","oftid":1610612749},"vls":{"q1":30,"s":127,"ftout":0,"stout":0,"ta":"MIL","tstsg":{"fga":93,"fgm":44,"tpa":27,"tpm":13,"fta":28,"ftm":26,"oreb":10,"dreb":33,"reb":43,"ast":27,"stl":9,"blk":3,"pf":23,"tov":14,"fbpts":16,"fbptsa":12,"fbptsm":5,"pip":52,"pipa":52,"pipm":26,"ble":4,"bpts":42,"tf":0,"scp":12,"tmreb":11,"tmtov":1,"potov":16},"pstsg":[{"fn":"Khris","ln":"Middleton","num":"22","pos":"SF","min":43,"sec":28,"totsec":2608,"fga":17,"fgm":7,"tpa":4,"tpm":0,"fta":4,"ftm":4,"oreb":0,"dreb":3,"reb":3,"ast":2,"stl":3,"blk":1,"pf":4,"pts":18,"tov":2,"fbpts":0,"fbptsa":2,"fbptsm":0,"pip":8,"pipa":7,"pipm":4,"court":1,"pid":203114,"pm":-8,"blka":2,"tf":0,"status":"A","memo":""},{"fn":"Giannis","ln":"Antetokounmpo","num":"34","pos":"PF","min":41,"sec":34,"totsec":2494,"fga":18,"fgm":9,"tpa":3,"tpm":1,"fta":9,"ftm":7,"oreb":2,"dreb":7,"reb":9,"ast":7,"stl":0,"blk":0,"pf":4,"pts":26,"tov":0,"fbpts":6,"fbptsa":3,"fbptsm":2,"pip":12,"pipa":11,"pipm":6,"court":1,"pid":203507,"pm":-6,"blka":1,"tf":0,"status":"A","memo":""},{"fn":"John","ln":"Henson","num":"31","pos":"C","min":25,"sec":44,"totsec":1544,"fga":8,"fgm":4,"tpa":0,"tpm":0,"fta":2,"ftm":2,"oreb":3,"dreb":4,"reb":7,"ast":2,"stl":0,"blk":1,"pf":3,"pts":10,"tov":1,"fbpts":0,"fbptsa":0,"fbptsm":0,"pip":8,"pipa":8,"pipm":4,"court":0,"pid":203089,"pm":-9,"blka":1,"tf":0,"status":"A","memo":""},{"fn":"Tony","ln":"Snell","num":"21","pos":"SG","min":18,"sec":2,"totsec":1082,"fga":4,"fgm":1,"tpa":1,"tpm":0,"fta":0,"ftm":0,"oreb":0,"dreb":2,"reb":2,"ast":0,"stl":1,"blk":0,"pf":0,"pts":2,"tov":1,"fbpts":0,"fbptsa":1,"fbptsm":0,"pip":2,"pipa":2,"pipm":1,"court":0,"pid":203503,"pm":-15,"blka":0,"tf":0,"status":"A","memo":""},{"fn":"Eric","ln":"Bledsoe","num":"6","pos":"PG","min":34,"sec":38,"totsec":2078,"fga":15,"fgm":9,"tpa":7,"tpm":5,"fta":6,"ftm":6,"oreb":1,"dreb":6,"reb":7,"ast":3,"stl":4,"blk":0,"pf":3,"pts":29,"tov":5,"fbpts":6,"fbptsa":4,"fbptsm":2,"pip":8,"pipa":8,"pipm":4,"court":1,"pid":202339,"pm":-9,"blka":2,"tf":0,"status":"A","memo":""},{"fn":"Malcolm","ln":"Brogdon","num":"13","pos":"","min":39,"sec":13,"totsec":2353,"fga":13,"fgm":7,"tpa":2,"tpm":1,"fta":0,"ftm":0,"oreb":3,"dreb":3,"reb":6,"ast":2,"stl":1,"blk":0,"pf":4,"pts":15,"tov":3,"fbpts":2,"fbptsa":1,"fbptsm":1,"pip":12,"pipa":10,"pipm":6,"court":1,"pid":1627763,"pm":9,"blka":2,"tf":0,"status":"A","memo":""},{"fn":"Thon","ln":"Maker","num":"7","pos":"","min":18,"sec":16,"totsec":1096,"fga":8,"fgm":4,"tpa":4,"tpm":3,"fta":5,"ftm":5,"oreb":0,"dreb":4,"reb":4,"ast":1,"stl":0,"blk":1,"pf":3,"pts":16,"tov":1,"fbpts":0,"fbptsa":0,"fbptsm":0,"pip":2,"pipa":4,"pipm":1,"court":0,"pid":1627748,"pm":6,"blka":0,"tf":0,"status":"A","memo":""},{"fn":"Matthew","ln":"Dellavedova","num":"8","pos":"","min":28,"sec":44,"totsec":1724,"fga":5,"fgm":2,"tpa":4,"tpm":2,"fta":0,"ftm":0,"oreb":1,"dreb":4,"reb":5,"ast":10,"stl":0,"blk":0,"pf":2,"pts":6,"tov":1,"fbpts":0,"fbptsa":0,"fbptsm":0,"pip":0,"pipa":1,"pipm":0,"court":1,"pid":203521,"pm":5,"blka":0,"tf":0,"status":"A","memo":""},{"fn":"Sean","ln":"Kilpatrick","num":"9","pos":"","min":10,"sec":2,"totsec":602,"fga":3,"fgm":1,"tpa":2,"tpm":1,"fta":2,"ftm":2,"oreb":0,"dreb":0,"reb":0,"ast":0,"stl":0,"blk":0,"pf":0,"pts":5,"tov":0,"fbpts":2,"fbptsa":1,"fbptsm":0,"pip":0,"pipa":1,"pipm":0,"court":0,"pid":203930,"pm":4,"blka":0,"tf":0,"status":"A","memo":""},{"fn":"Jason","ln":"Terry","num":"3","pos":"","min":5,"sec":19,"totsec":319,"fga":2,"fgm":0,"tpa":0,"tpm":0,"fta":0,"ftm":0,"oreb":0,"dreb":0,"reb":0,"ast":0,"stl":0,"blk":0,"pf":0,"pts":0,"tov":0,"fbpts":0,"fbptsa":0,"fbptsm":0,"pip":0,"pipa":0,"pipm":0,"court":0,"pid":1891,"pm":3,"blka":0,"tf":0,"status":"A","memo":""},{"fn":"Sterling","ln":"Brown","num":"23","pos":"","min":0,"sec":0,"totsec":0,"fga":0,"fgm":0,"tpa":0,"tpm":0,"fta":0,"ftm":0,"oreb":0,"dreb":0,"reb":0,"ast":0,"stl":0,"blk":0,"pf":0,"pts":0,"tov":0,"fbpts":0,"fbptsa":0,"fbptsm":0,"pip":0,"pipa":0,"pipm":0,"court":0,"pid":1628425,"pm":0,"blka":0,"tf":0,"status":"A","memo":""},{"fn":"DeAndre","ln":"Liggins","num":"25","pos":"","min":0,"sec":0,"totsec":0,"fga":0,"fgm":0,"tpa":0,"tpm":0,"fta":0,"ftm":0,"oreb":0,"dreb":0,"reb":0,"ast":0,"stl":0,"blk":0,"pf":0,"pts":0,"tov":0,"fbpts":0,"fbptsa":0,"fbptsm":0,"pip":0,"pipa":0,"pipm":0,"court":0,"pid":202732,"pm":0,"blka":0,"tf":0,"status":"A","memo":""},{"fn":"Rashad","ln":"Vaughn","num":"20","pos":"","min":0,"sec":0,"totsec":0,"fga":0,"fgm":0,"tpa":0,"tpm":0,"fta":0,"ftm":0,"oreb":0,"dreb":0,"reb":0,"ast":0,"stl":0,"blk":0,"pf":0,"pts":0,"tov":0,"fbpts":0,"fbptsa":0,"fbptsm":0,"pip":0,"pipa":0,"pipm":0,"court":0,"pid":1626173,"pm":0,"blka":0,"tf":0,"status":"A","memo":""},{"fn":"Joel","ln":"Bolomboy","num":"24","pos":"","min":0,"sec":0,"totsec":0,"fga":0,"fgm":0,"tpa":0,"tpm":0,"fta":0,"ftm":0,"oreb":0,"dreb":0,"reb":0,"ast":0,"stl":0,"blk":0,"pf":0,"pts":0,"tov":0,"fbpts":0,"fbptsa":0,"fbptsm":0,"pip":0,"pipa":0,"pipm":0,"court":0,"pid":1627762,"pm":0,"blka":0,"tf":0,"status":"I","memo":""},{"fn":"Jabari","ln":"Parker","num":"12","pos":"","min":0,"sec":0,"totsec":0,"fga":0,"fgm":0,"tpa":0,"tpm":0,"fta":0,"ftm":0,"oreb":0,"dreb":0,"reb":0,"ast":0,"stl":0,"blk":0,"pf":0,"pts":0,"tov":0,"fbpts":0,"fbptsa":0,"fbptsm":0,"pip":0,"pipa":0,"pipm":0,"court":0,"pid":203953,"pm":0,"blka":0,"tf":0,"status":"I","memo":""},{"fn":"Mirza","ln":"Teletovic","num":"35","pos":"","min":0,"sec":0,"totsec":0,"fga":0,"fgm":0,"tpa":0,"tpm":0,"fta":0,"ftm":0,"oreb":0,"dreb":0,"reb":0,"ast":0,"stl":0,"blk":0,"pf":0,"pts":0,"tov":0,"fbpts":0,"fbptsa":0,"fbptsm":0,"pip":0,"pipa":0,"pipm":0,"court":0,"pid":203141,"pm":0,"blka":0,"tf":0,"status":"I","memo":""},{"fn":"D.J.","ln":"Wilson","num":"5","pos":"","min":0,"sec":0,"totsec":0,"fga":0,"fgm":0,"tpa":0,"tpm":0,"fta":0,"ftm":0,"oreb":0,"dreb":0,"reb":0,"ast":0,"stl":0,"blk":0,"pf":0,"pts":0,"tov":0,"fbpts":0,"fbptsa":0,"fbptsm":0,"pip":0,"pipa":0,"pipm":0,"court":0,"pid":1628391,"pm":0,"blka":0,"tf":0,"status":"I","memo":""}],"tn":"Bucks","tc":"Milwaukee","tid":1610612749,"q2":26,"q3":28,"q4":30,"ot1":13,"ot2":0,"ot3":0,"ot4":0,"ot5":0,"ot6":0,"ot7":0,"ot8":0,"ot9":0,"ot10":0},"hls":{"q1":35,"s":131,"ftout":2,"stout":0,"ta":"TOR","tstsg":{"fga":91,"fgm":45,"tpa":33,"tpm":14,"fta":33,"ftm":27,"oreb":6,"dreb":34,"reb":40,"ast":25,"stl":8,"blk":8,"pf":20,"tov":12,"fbpts":5,"fbptsa":7,"fbptsm":2,"pip":48,"pipa":42,"pipm":24,"ble":11,"bpts":35,"tf":0,"scp":13,"tmreb":9,"tmtov":1,"potov":13},"pstsg":[{"fn":"OG","ln":"Anunoby","num":"3","pos":"SF","min":34,"sec":51,"totsec":2091,"fga":0,"fgm":0,"tpa":0,"tpm":0,"fta":2,"ftm":1,"oreb":0,"dreb":6,"reb":6,"ast":2,"stl":0,"blk":0,"pf":1,"pts":1,"tov":1,"fbpts":0,"fbptsa":0,"fbptsm":0,"pip":0,"pipa":0,"pipm":0,"court":1,"pid":1628384,"pm":16,"blka":0,"tf":0,"status":"A","memo":""},{"fn":"Serge","ln":"Ibaka","num":"9","pos":"PF","min":37,"sec":36,"totsec":2256,"fga":19,"fgm":5,"tpa":5,"tpm":0,"fta":1,"ftm":1,"oreb":2,"dreb":6,"reb":8,"ast":2,"stl":2,"blk":4,"pf":2,"pts":11,"tov":2,"fbpts":0,"fbptsa":1,"fbptsm":0,"pip":8,"pipa":9,"pipm":4,"court":1,"pid":201586,"pm":8,"blka":1,"tf":0,"status":"A","memo":""},{"fn":"Jonas","ln":"Valanciunas","num":"17","pos":"C","min":16,"sec":18,"totsec":978,"fga":3,"fgm":2,"tpa":0,"tpm":0,"fta":2,"ftm":2,"oreb":0,"dreb":5,"reb":5,"ast":0,"stl":0,"blk":0,"pf":1,"pts":6,"tov":1,"fbpts":0,"fbptsa":0,"fbptsm":0,"pip":4,"pipa":3,"pipm":2,"court":0,"pid":202685,"pm":7,"blka":0,"tf":0,"status":"A","memo":""},{"fn":"DeMar","ln":"DeRozan","num":"10","pos":"SG","min":43,"sec":27,"totsec":2607,"fga":29,"fgm":17,"tpa":9,"tpm":5,"fta":13,"ftm":13,"oreb":1,"dreb":4,"reb":5,"ast":8,"stl":1,"blk":1,"pf":4,"pts":52,"tov":2,"fbpts":5,"fbptsa":3,"fbptsm":2,"pip":14,"pipa":13,"pipm":7,"court":1,"pid":201942,"pm":9,"blka":0,"tf":0,"status":"A","memo":""},{"fn":"Kyle","ln":"Lowry","num":"7","pos":"PG","min":41,"sec":4,"totsec":2464,"fga":13,"fgm":7,"tpa":10,"tpm":5,"fta":10,"ftm":7,"oreb":1,"dreb":5,"reb":6,"ast":6,"stl":1,"blk":1,"pf":5,"pts":26,"tov":3,"fbpts":0,"fbptsa":1,"fbptsm":0,"pip":2,"pipa":2,"pipm":1,"court":1,"pid":200768,"pm":11,"blka":0,"tf":0,"status":"A","memo":""},{"fn":"Jakob","ln":"Poeltl","num":"42","pos":"","min":17,"sec":11,"totsec":1031,"fga":3,"fgm":2,"tpa":0,"tpm":0,"fta":0,"ftm":0,"oreb":1,"dreb":1,"reb":2,"ast":2,"stl":1,"blk":0,"pf":3,"pts":4,"tov":0,"fbpts":0,"fbptsa":0,"fbptsm":0,"pip":4,"pipa":2,"pipm":2,"court":0,"pid":1627751,"pm":-7,"blka":0,"tf":0,"status":"A","memo":""},{"fn":"CJ","ln":"Miles","num":"0","pos":"","min":17,"sec":15,"totsec":1035,"fga":7,"fgm":3,"tpa":4,"tpm":2,"fta":0,"ftm":0,"oreb":0,"dreb":4,"reb":4,"ast":1,"stl":1,"blk":0,"pf":2,"pts":8,"tov":0,"fbpts":0,"fbptsa":1,"fbptsm":0,"pip":2,"pipa":2,"pipm":1,"court":0,"pid":101139,"pm":-12,"blka":0,"tf":0,"status":"A","memo":""},{"fn":"Pascal","ln":"Siakam","num":"43","pos":"","min":16,"sec":26,"totsec":986,"fga":3,"fgm":2,"tpa":0,"tpm":0,"fta":0,"ftm":0,"oreb":1,"dreb":0,"reb":1,"ast":0,"stl":0,"blk":0,"pf":1,"pts":4,"tov":1,"fbpts":0,"fbptsa":0,"fbptsm":0,"pip":4,"pipa":2,"pipm":2,"court":0,"pid":1627783,"pm":-8,"blka":1,"tf":0,"status":"A","memo":""},{"fn":"Delon","ln":"Wright","num":"55","pos":"","min":19,"sec":0,"totsec":1140,"fga":7,"fgm":3,"tpa":2,"tpm":0,"fta":3,"ftm":2,"oreb":0,"dreb":1,"reb":1,"ast":2,"stl":1,"blk":2,"pf":0,"pts":8,"tov":1,"fbpts":0,"fbptsa":0,"fbptsm":0,"pip":6,"pipa":5,"pipm":3,"court":0,"pid":1626153,"pm":2,"blka":0,"tf":0,"status":"A","memo":""},{"fn":"Fred","ln":"VanVleet","num":"23","pos":"","min":21,"sec":51,"totsec":1311,"fga":7,"fgm":4,"tpa":3,"tpm":2,"fta":2,"ftm":1,"oreb":0,"dreb":2,"reb":2,"ast":2,"stl":1,"blk":0,"pf":1,"pts":11,"tov":1,"fbpts":0,"fbptsa":1,"fbptsm":0,"pip":4,"pipa":4,"pipm":2,"court":1,"pid":1627832,"pm":-6,"blka":1,"tf":0,"status":"A","memo":""},{"fn":"Lucas","ln":"Nogueira","num":"92","pos":"","min":0,"sec":0,"totsec":0,"fga":0,"fgm":0,"tpa":0,"tpm":0,"fta":0,"ftm":0,"oreb":0,"dreb":0,"reb":0,"ast":0,"stl":0,"blk":0,"pf":0,"pts":0,"tov":0,"fbpts":0,"fbptsa":0,"fbptsm":0,"pip":0,"pipa":0,"pipm":0,"court":0,"pid":203512,"pm":0,"blka":0,"tf":0,"status":"A","memo":""},{"fn":"Norman","ln":"Powell","num":"24","pos":"","min":0,"sec":0,"totsec":0,"fga":0,"fgm":0,"tpa":0,"tpm":0,"fta":0,"ftm":0,"oreb":0,"dreb":0,"reb":0,"ast":0,"stl":0,"blk":0,"pf":0,"pts":0,"tov":0,"fbpts":0,"fbptsa":0,"fbptsm":0,"pip":0,"pipa":0,"pipm":0,"court":0,"pid":1626181,"pm":0,"blka":0,"tf":0,"status":"A","memo":""},{"fn":"Lorenzo","ln":"Brown","num":"4","pos":"","min":0,"sec":0,"totsec":0,"fga":0,"fgm":0,"tpa":0,"tpm":0,"fta":0,"ftm":0,"oreb":0,"dreb":0,"reb":0,"ast":0,"stl":0,"blk":0,"pf":0,"pts":0,"tov":0,"fbpts":0,"fbptsa":0,"fbptsm":0,"pip":0,"pipa":0,"pipm":0,"court":0,"pid":203485,"pm":0,"blka":0,"tf":0,"status":"I","memo":""},{"fn":"Bruno","ln":"Caboclo","num":"5","pos":"","min":0,"sec":0,"totsec":0,"fga":0,"fgm":0,"tpa":0,"tpm":0,"fta":0,"ftm":0,"oreb":0,"dreb":0,"reb":0,"ast":0,"stl":0,"blk":0,"pf":0,"pts":0,"tov":0,"fbpts":0,"fbptsa":0,"fbptsm":0,"pip":0,"pipa":0,"pipm":0,"court":0,"pid":203998,"pm":0,"blka":0,"tf":0,"status":"I","memo":""},{"fn":"Alfonzo","ln":"McKinnie","num":"34","pos":"","min":0,"sec":0,"totsec":0,"fga":0,"fgm":0,"tpa":0,"tpm":0,"fta":0,"ftm":0,"oreb":0,"dreb":0,"reb":0,"ast":0,"stl":0,"blk":0,"pf":0,"pts":0,"tov":0,"fbpts":0,"fbptsa":0,"fbptsm":0,"pip":0,"pipa":0,"pipm":0,"court":0,"pid":1628035,"pm":0,"blka":0,"tf":0,"status":"I","memo":""},{"fn":"Malcolm","ln":"Miller","num":"13","pos":"","min":0,"sec":0,"totsec":0,"fga":0,"fgm":0,"tpa":0,"tpm":0,"fta":0,"ftm":0,"oreb":0,"dreb":0,"reb":0,"ast":0,"stl":0,"blk":0,"pf":0,"pts":0,"tov":0,"fbpts":0,"fbptsa":0,"fbptsm":0,"pip":0,"pipa":0,"pipm":0,"court":0,"pid":1626259,"pm":0,"blka":0,"tf":0,"status":"I","memo":""}],"tn":"Raptors","tc":"Toronto","tid":1610612761,"q2":25,"q3":28,"q4":26,"ot1":17,"ot2":0,"ot3":0,"ot4":0,"ot5":0,"ot6":0,"ot7":0,"ot8":0,"ot9":0,"ot10":0},"offs":{"off":[{"fn":"Derek","ln":"Richardson","num":"63"},{"fn":"Gary","ln":"Zielinski","num":"59"},{"fn":"Ed","ln":"Malloy","num":"14"}]},"an":"Air Canada Centre","at":19800,"gsts":{"lc":12,"tt":10},"dur":"2:31"}}