{"g":{"mid":1515810387597,"gid":"0021700618","gdte":"2018-01-12","htm":"2018-01-12T19:00:00","vtm":"2018-01-12T17:00:00","etm":"2018-01-12T19:00:00","gdtutc":"2018-01-13","utctm":"00:00","ac":"Charlotte","as":"NC","gcode":"20180112/UTACHA","next":"http://data.nba.com/data/v2015/json/mobile_teams/nba/2017/scores/gamedetail/0021700618_gamedetail.json","ar":0,"p":4,"st":3,"stt":"Final","cl":"00:00.0","lpla":{"evt":658,"cl":"00:00.0","de":"End Period","locX":0,"locY":-80,"opt1":0,"opt2":0,"mtype":0,"etype":13,"opid":"","tid":0,"pid":0,"hs":99,"vs":88,"epid":"","oftid":1610612762},"vls":{"q1":25,"s":88,"ftout":1,"stout":0,"ta":"UTA","tstsg":{"fga":77,"fgm":28,"tpa":35,"tpm":12,"fta":23,"ftm":20,"oreb":8,"dreb":37,"reb":45,"ast":19,"stl":5,"blk":8,"pf":26,"tov":14,"fbpts":5,"fbptsa":6,"fbptsm":2,"pip":26,"pipa":28,"pipm":13,"ble":7,"bpts":32,"tf":0,"scp":7,"tmreb":5,"tmtov":1,"potov":4},"pstsg":[{"fn":"Joe","ln":"Ingles","num":"2","pos":"SF","min":34,"sec":30,"totsec":2070,"fga":6,"fgm":1,"tpa":3,"tpm":0,"fta":0,"ftm":0,"oreb":0,"dreb":5,"reb":5,"ast":6,"stl":2,"blk":1,"pf":5,"pts":2,"tov":3,"fbpts":0,"fbptsa":0,"fbptsm":0,"pip":2,"pipa":3,"pipm":1,"court":1,"pid":204060,"pm":-21,"blka":0,"tf":0,"status":"A","memo":""},{"fn":"Thabo","ln":"Sefolosha","num":"22","pos":"PF","min":16,"sec":30,"totsec":990,"fga":5,"fgm":3,"tpa":1,"tpm":1,"fta":0,"ftm":0,"oreb":2,"dreb":2,"reb":4,"ast":2,"stl":0,"blk":1,"pf":2,"pts":7,"tov":1,"fbpts":0,"fbptsa":0,"fbptsm":0,"pip":4,"pipa":3,"pipm":2,"court":0,"pid":200757,"pm":-2,"blka":1,"tf":0,"status":"A","memo":""},{"fn":"Derrick","ln":"Favors","num":"15","pos":"C","min":28,"sec":53,"totsec":1733,"fga":4,"fgm":2,"tpa":0,"tpm":0,"fta":2,"ftm":1,"oreb":1,"dreb":6,"reb":7,"ast":4,"stl":0,"blk":2,"pf":4,"pts":5,"tov":0,"fbpts":0,"fbptsa":0,"fbptsm":0,"pip":4,"pipa":3,"pipm":2,"court":1,"pid":202324,"pm":-19,"blka":0,"tf":0,"status":"A","memo":""},{"fn":"Donovan","ln":"Mitchell","num":"45","pos":"SG","min":36,"sec":47,"totsec":2207,"fga":20,"fgm":10,"tpa":11,"tpm":5,"fta":11,"ftm":10,"oreb":1,"dreb":4,"reb":5,"ast":0,"stl":2,"blk":0,"pf":2,"pts":35,"tov":5,"fbpts":1,"fbptsa":1,"fbptsm":0,"pip":8,"pipa":7,"pipm":4,"court":1,"pid":1628378,"pm":-18,"blka":0,"tf":0,"status":"A","memo":""},{"fn":"Ricky","ln":"Rubio","num":"3","pos":"PG","min":28,"sec":10,"totsec":1690,"fga":11,"fgm":3,"tpa":3,"tpm":1,"fta":0,"ftm":0,"oreb":1,"dreb":6,"reb":7,"ast":4,"stl":0,"blk":1,"pf":2,"pts":7,"tov":2,"fbpts":2,"fbptsa":1,"fbptsm":1,"pip":0,"pipa":2,"pipm":0,"court":0,"pid":201937,"pm":-2,"blka":0,"tf":0,"status":"A","memo":""},{"fn":"Rodney","ln":"Hood","num":"5","pos":"","min":26,"sec":1,"totsec":1561,"fga":13,"fgm":4,"tpa":9,"tpm":3,"fta":4,"ftm":4,"oreb":0,"dreb":1,"reb":1,"ast":1,"stl":0,"blk":0,"pf":2,"pts":15,"tov":0,"fbpts":0,"fbptsa":0,"fbptsm":0,"pip":2,"pipa":2,"pipm":1,"court":1,"pid":203918,"pm":7,"blka":0,"tf":0,"status":"A","memo":""},{"fn":"Joe","ln":"Johnson","num":"6","pos":"","min":25,"sec":51,"totsec":1551,"fga":8,"fgm":2,"tpa":4,"tpm":1,"fta":0,"ftm":0,"oreb":0,"dreb":3,"reb":3,"ast":1,"stl":0,"blk":1,"pf":3,"pts":5,"tov":1,"fbpts":0,"fbptsa":1,"fbptsm":0,"pip":2,"pipa":2,"pipm":1,"court":1,"pid":2207,"pm":-6,"blka":0,"tf":0,"status":"A","memo":""},{"fn":"Ekpe","ln":"Udoh","num":"33","pos":"","min":19,"sec":7,"totsec":1147,"fga":3,"fgm":0,"tpa":0,"tpm":0,"fta":2,"ftm":1,"oreb":2,"dreb":1,"reb":3,"ast":0,"stl":1,"blk":2,"pf":1,"pts":1,"tov":0,"fbpts":0,"fbptsa":0,"fbptsm":0,"pip":0,"pipa":3,"pipm":0,"court":0,"pid":202327,"pm":8,"blka":1,"tf":0,"status":"A","memo":""},{"fn":"Royce","ln":"O'Neale","num":"23","pos":"","min":18,"sec":57,"totsec":1137,"fga":6,"fgm":3,"tpa":3,"tpm":1,"fta":4,"ftm":4,"oreb":1,"dreb":9,"reb":10,"ast":1,"stl":0,"blk":0,"pf":4,"pts":11,"tov":2,"fbpts":2,"fbptsa":2,"fbptsm":1,"pip":4,"pipa":3,"pipm":2,"court":0,"pid":1626220,"pm":-1,"blka":0,"tf":0,"status":"A","memo":""},{"fn":"Jonas","ln":"Jerebko","num":"8","pos":"","min":5,"sec":13,"totsec":313,"fga":1,"fgm":0,"tpa":1,"tpm":0,"fta":0,"ftm":0,"oreb":0,"dreb":0,"reb":0,"ast":0,"stl":0,"blk":0,"pf":1,"pts":0,"tov":0,"fbpts":0,"fbptsa":1,"fbptsm":0,"pip":0,"pipa":0,"pipm":0,"court":0,"pid":201973,"pm":-1,"blka":0,"tf":0,"status":"A","memo":""},{"fn":"Tony","ln":"Bradley","num":"13","pos":"","min":0,"sec":0,"totsec":0,"fga":0,"fgm":0,"tpa":0,"tpm":0,"fta":0,"ftm":0,"oreb":0,"dreb":0,"reb":0,"ast":0,"stl":0,"blk":0,"pf":0,"pts":0,"tov":0,"fbpts":0,"fbptsa":0,"fbptsm":0,"pip":0,"pipa":0,"pipm":0,"court":0,"pid":1628396,"pm":0,"blka":0,"tf":0,"status":"A","memo":""},{"fn":"Alec","ln":"Burks","num":"10","pos":"","min":0,"sec":0,"totsec":0,"fga":0,"fgm":0,"tpa":0,"tpm":0,"fta":0,"ftm":0,"oreb":0,"dreb":0,"reb":0,"ast":0,"stl":0,"blk":0,"pf":0,"pts":0,"tov":0,"fbpts":0,"fbptsa":0,"fbptsm":0,"pip":0,"pipa":0,"pipm":0,"court":0,"pid":202692,"pm":0,"blka":0,"tf":0,"status":"A","memo":""},{"fn":"Naz","ln":"Mitrou-Long","num":"30","pos":"","min":0,"sec":0,"totsec":0,"fga":0,"fgm":0,"tpa":0,"tpm":0,"fta":0,"ftm":0,"oreb":0,"dreb":0,"reb":0,"ast":0,"stl":0,"blk":0,"pf":0,"pts":0,"tov":0,"fbpts":0,"fbptsa":0,"fbptsm":0,"pip":0,"pipa":0,"pipm":0,"court":0,"pid":1628513,"pm":0,"blka":0,"tf":0,"status":"A","memo":""},{"fn":"Dante","ln":"Exum","num":"11","pos":"","min":0,"sec":0,"totsec":0,"fga":0,"fgm":0,"tpa":0,"tpm":0,"fta":0,"ftm":0,"oreb":0,"dreb":0,"reb":0,"ast":0,"stl":0,"blk":0,"pf":0,"pts":0,"tov":0,"fbpts":0,"fbptsa":0,"fbptsm":0,"pip":0,"pipa":0,"pipm":0,"court":0,"pid":203957,"pm":0,"blka":0,"tf":0,"status":"I","memo":""},{"fn":"Rudy","ln":"Gobert","num":"27","pos":"","min":0,"sec":0,"totsec":0,"fga":0,"fgm":0,"tpa":0,"tpm":0,"fta":0,"ftm":0,"oreb":0,"dreb":0,"reb":0,"ast":0,"stl":0,"blk":0,"pf":0,"pts":0,"tov":0,"fbpts":0,"fbptsa":0,"fbptsm":0,"pip":0,"pipa":0,"pipm":0,"court":0,"pid":203497,"pm":0,"blka":0,"tf":0,"status":"I","memo":""},{"fn":"Erik","ln":"McCree","num":"21","pos":"","min":0,"sec":0,"totsec":0,"fga":0,"fgm":0,"tpa":0,"tpm":0,"fta":0,"ftm":0,"oreb":0,"dreb":0,"reb":0,"ast":0,"stl":0,"blk":0,"pf":0,"pts":0,"tov":0,"fbpts":0,"fbptsa":0,"fbptsm":0,"pip":0,"pipa":0,"pipm":0,"court":0,"pid":1628571,"pm":0,"blka":0,"tf":0,"status":"I","memo":""},{"fn":"Raul","ln":"Neto","num":"25","pos":"","min":0,"sec":0,"totsec":0,"fga":0,"fgm":0,"tpa":0,"tpm":0,"fta":0,"ftm":0,"oreb":0,"dreb":0,"reb":0,"ast":0,"stl":0,"blk":0,"pf":0,"pts":0,"tov":0,"fbpts":0,"fbptsa":0,"fbptsm":0,"pip":0,"pipa":0,"pipm":0,"court":0,"pid":203526,"pm":0,"blka":0,"tf":0,"status":"I","memo":""}],"tn":"Jazz","tc":"Utah","tid":1610612762,"q2":21,"q3":26,"q4":16,"ot1":0,"ot2":0,"ot3":0,"ot4":0,"ot5":0,"ot6":0,"ot7":0,"ot8":0,"ot9":0,"ot10":0},"hls":{"q1":25,"s":99,"ftout":1,"stout":0,"ta":"CHA","tstsg":{"fga":78,"fgm":32,"tpa":27,"tpm":9,"fta":34,"ftm":26,"oreb":8,"dreb":38,"reb":46,"ast":17,"stl":8,"blk":2,"pf":19,"tov":12,"fbpts":11,"fbptsa":4,"fbptsm":4,"pip":32,"pipa":30,"pipm":16,"ble":11,"bpts":31,"tf":1,"scp":13,"tmreb":10,"tmtov":1,"potov":14},"pstsg":[{"fn":"Michael","ln":"Kidd-Gilchrist","num":"14","pos":"SF","min":26,"sec":30,"totsec":1590,"fga":7,"fgm":3,"tpa":0,"tpm":0,"fta":6,"ftm":6,"oreb":2,"dreb":3,"reb":5,"ast":0,"stl":2,"blk":0,"pf":1,"pts":12,"tov":1,"fbpts":6,"fbptsa":2,"fbptsm":2,"pip":6,"pipa":5,"pipm":3,"court":1,"pid":203077,"pm":14,"blka":2,"tf":0,"status":"A","memo":""},{"fn":"Marvin","ln":"Williams","num":"2","pos":"PF","min":26,"sec":49,"totsec":1609,"fga":11,"fgm":5,"tpa":8,"tpm":3,"fta":2,"ftm":2,"oreb":1,"dreb":6,"reb":7,"ast":1,"stl":3,"blk":0,"pf":4,"pts":15,"tov":3,"fbpts":0,"fbptsa":0,"fbptsm":0,"pip":4,"pipa":3,"pipm":2,"court":1,"pid":101107,"pm":13,"blka":1,"tf":0,"status":"A","memo":""},{"fn":"Dwight","ln":"Howard","num":"12","pos":"C","min":32,"sec":42,"totsec":1962,"fga":9,"fgm":2,"tpa":0,"tpm":0,"fta":10,"ftm":4,"oreb":2,"dreb":11,"reb":13,"ast":1,"stl":1,"blk":1,"pf":4,"pts":8,"tov":2,"fbpts":0,"fbptsa":0,"fbptsm":0,"pip":4,"pipa":8,"pipm":2,"court":1,"pid":2730,"pm":14,"blka":3,"tf":1,"status":"A","memo":""},{"fn":"Nicolas","ln":"Batum","num":"5","pos":"SG","min":36,"sec":5,"totsec":2165,"fga":11,"fgm":5,"tpa":5,"tpm":1,"fta":0,"ftm":0,"oreb":0,"dreb":3,"reb":3,"ast":5,"stl":1,"blk":0,"pf":0,"pts":11,"tov":2,"fbpts":2,"fbptsa":1,"fbptsm":1,"pip":2,"pipa":1,"pipm":1,"court":1,"pid":201587,"pm":12,"blka":0,"tf":0,"status":"A","memo":""},{"fn":"Kemba","ln":"Walker","num":"15","pos":"PG","min":37,"sec":12,"totsec":2232,"fga":14,"fgm":5,"tpa":6,"tpm":4,"fta":9,"ftm":8,"oreb":0,"dreb":2,"reb":2,"ast":6,"stl":0,"blk":0,"pf":2,"pts":22,"tov":2,"fbpts":3,"fbptsa":1,"fbptsm":1,"pip":0,"pipa":1,"pipm":0,"court":1,"pid":202689,"pm":17,"blka":1,"tf":0,"status":"A","memo":""},{"fn":"Frank","ln":"Kaminsky","num":"44","pos":"","min":26,"sec":45,"totsec":1605,"fga":13,"fgm":6,"tpa":4,"tpm":1,"fta":3,"ftm":3,"oreb":1,"dreb":2,"reb":3,"ast":1,"stl":0,"blk":0,"pf":3,"pts":16,"tov":1,"fbpts":0,"fbptsa":0,"fbptsm":0,"pip":8,"pipa":6,"pipm":4,"court":0,"pid":1626163,"pm":-1,"blka":1,"tf":0,"status":"A","memo":""},{"fn":"Jeremy","ln":"Lamb","num":"3","pos":"","min":21,"sec":30,"totsec":1290,"fga":8,"fgm":5,"tpa":2,"tpm":0,"fta":2,"ftm":1,"oreb":0,"dreb":8,"reb":8,"ast":1,"stl":0,"blk":0,"pf":3,"pts":11,"tov":0,"fbpts":0,"fbptsa":0,"fbptsm":0,"pip":6,"pipa":4,"pipm":3,"court":0,"pid":203087,"pm":-3,"blka":0,"tf":0,"status":"A","memo":""},{"fn":"Michael","ln":"Carter-Williams","num":"10","pos":"","min":13,"sec":4,"totsec":784,"fga":1,"fgm":1,"tpa":0,"tpm":0,"fta":0,"ftm":0,"oreb":1,"dreb":2,"reb":3,"ast":1,"stl":1,"blk":1,"pf":2,"pts":2,"tov":0,"fbpts":0,"fbptsa":0,"fbptsm":0,"pip":2,"pipa":1,"pipm":1,"court":0,"pid":203487,"pm":-3,"blka":0,"tf":0,"status":"A","memo":""},{"fn":"Johnny","ln":"O'Bryant III","num":"8","pos":"","min":7,"sec":13,"totsec":433,"fga":2,"fgm":0,"tpa":1,"tpm":0,"fta":0,"ftm":0,"oreb":0,"dreb":0,"reb":0,"ast":0,"stl":0,"blk":0,"pf":0,"pts":0,"tov":0,"fbpts":0,"fbptsa":0,"fbptsm":0,"pip":0,"pipa":1,"pipm":0,"court":0,"pid":203948,"pm":-6,"blka":0,"tf":0,"status":"A","memo":""},{"fn":"Treveon","ln":"Graham","num":"21","pos":"","min":12,"sec":9,"totsec":729,"fga":2,"fgm":0,"tpa":1,"tpm":0,"fta":2,"ftm":2,"oreb":1,"dreb":1,"reb":2,"ast":1,"stl":0,"blk":0,"pf":0,"pts":2,"tov":1,"fbpts":0,"fbptsa":0,"fbptsm":0,"pip":0,"pipa":0,"pipm":0,"court":0,"pid":1626203,"pm":-2,"blka":0,"tf":0,"status":"A","memo":""},{"fn":"Malik","ln":"Monk","num":"1","pos":"","min":0,"sec":0,"totsec":0,"fga":0,"fgm":0,"tpa":0,"tpm":0,"fta":0,"ftm":0,"oreb":0,"dreb":0,"reb":0,"ast":0,"stl":0,"blk":0,"pf":0,"pts":0,"tov":0,"fbpts":0,"fbptsa":0,"fbptsm":0,"pip":0,"pipa":0,"pipm":0,"court":0,"pid":1628370,"pm":0,"blka":0,"tf":0,"status":"A","memo":""},{"fn":"Julyan","ln":"Stone","num":"32","pos":"","min":0,"sec":0,"totsec":0,"fga":0,"fgm":0,"tpa":0,"tpm":0,"fta":0,"ftm":0,"oreb":0,"dreb":0,"reb":0,"ast":0,"stl":0,"blk":0,"pf":0,"pts":0,"tov":0,"fbpts":0,"fbptsa":0,"fbptsm":0,"pip":0,"pipa":0,"pipm":0,"court":0,"pid":202933,"pm":0,"blka":0,"tf":0,"status":"A","memo":""},{"fn":"Dwayne","ln":"Bacon","num":"7","pos":"","min":0,"sec":0,"totsec":0,"fga":0,"fgm":0,"tpa":0,"tpm":0,"fta":0,"ftm":0,"oreb":0,"dreb":0,"reb":0,"ast":0,"stl":0,"blk":0,"pf":0,"pts":0,"tov":0,"fbpts":0,"fbptsa":0,"fbptsm":0,"pip":0,"pipa":0,"pipm":0,"court":0,"pid":1628407,"pm":0,"blka":0,"tf":0,"status":"I","memo":""},{"fn":"Mangok","ln":"Mathiang","num":"9","pos":"","min":0,"sec":0,"totsec":0,"fga":0,"fgm":0,"tpa":0,"tpm":0,"fta":0,"ftm":0,"oreb":0,"dreb":0,"reb":0,"ast":0,"stl":0,"blk":0,"pf":0,"pts":0,"tov":0,"fbpts":0,"fbptsa":0,"fbptsm":0,"pip":0,"pipa":0,"pipm":0,"court":0,"pid":1628493,"pm":0,"blka":0,"tf":0,"status":"I","memo":""},{"fn":"Marcus","ln":"Paige","num":"4","pos":"","min":0,"sec":0,"totsec":0,"fga":0,"fgm":0,"tpa":0,"tpm":0,"fta":0,"ftm":0,"oreb":0,"dreb":0,"reb":0,"ast":0,"stl":0,"blk":0,"pf":0,"pts":0,"tov":0,"fbpts":0,"fbptsa":0,"fbptsm":0,"pip":0,"pipa":0,"pipm":0,"court":0,"pid":1627779,"pm":0,"blka":0,"tf":0,"status":"I","memo":""},{"fn":"Cody","ln":"Zeller","num":"40","pos":"","min":0,"sec":0,"totsec":0,"fga":0,"fgm":0,"tpa":0,"tpm":0,"fta":0,"ftm":0,"oreb":0,"dreb":0,"reb":0,"ast":0,"stl":0,"blk":0,"pf":0,"pts":0,"tov":0,"fbpts":0,"fbptsa":0,"fbptsm":0,"pip":0,"pipa":0,"pipm":0,"court":0,"pid":203469,"pm":0,"blka":0,"tf":0,"status":"I","memo":""}],"tn":"Hornets","tc":"Charlotte","tid":1610612766,"q2":27,"q3":22,"q4":25,"ot1":0,"ot2":0,"ot3":0,"ot4":0,"ot5":0,"ot6":0,"ot7":0,"ot8":0,"ot9":0,"ot10":0},"offs":{"off":[{"fn":"Bill","ln":"Spooner","num":"22"},{"fn":"Nick","ln":"Buchert","num":"3"},{"fn":"Jason","ln":"Goldenberg","num":"35"}]},"an":"Spectrum Center","at":14848,"gsts":{"lc":10,"tt":17},"dur":"0:00"}}